Lab06/CPU Programming Tools-20240416/alu.v
`define REG_SIZE 8
`define REG_ADDRESS_SIZE 3


module mov_module (DATA2,RESULT);
    input [`REG_SIZE-1:0] DATA2;
    output [`REG_SIZE-1:0] RESULT;

    assign RESULT = DATA2;

endmodule

module add_module (DATA1,DATA2,RESULT);
    input [`REG_SIZE-1:0] DATA1;
    input [`REG_SIZE-1:0] DATA2;
    output reg [`REG_SIZE-1:0] RESULT;
    
    always @(*) 
    begin   // add - sub
    if (DATA2 < 0)  // or we can use (DATA2[7]) as the condition
        RESULT = DATA1 - DATA2;
    else
        RESULT = DATA1 + DATA2;
    end

endmodule

module and_module (DATA1,DATA2,RESULT);
    input [`REG_SIZE-1:0] DATA1;
    input [`REG_SIZE-1:0] DATA2;
    output [`REG_SIZE-1:0] RESULT;

    assign RESULT = DATA1 & DATA2;

endmodule

module or_module (DATA1,DATA2,RESULT);
    input [`REG_SIZE-1:0] DATA1;
    input [`REG_SIZE-1:0] DATA2;
    output [`REG_SIZE-1:0] RESULT;

    assign RESULT = DATA1 | DATA2;


endmodule

module alu (DATA1,DATA2,RESULT,SELECT);
    input [`REG_SIZE-1:0] DATA1;
    input [`REG_SIZE-1:0] DATA2;
    output reg [`REG_SIZE-1:0] RESULT; // if we want to use wire insted of reg , we woud have to use 'assign' to do that use internal_RESULT and assign to RESULT at the end
    input [`REG_ADDRESS_SIZE-1:0] SELECT;

    // making wires to have each module's answer.
    wire [`REG_SIZE-1:0] MOV_RESULT;     
    wire [`REG_SIZE-1:0] ADD_RESULT;
    wire [`REG_SIZE-1:0] AND_RESULT;
    wire [`REG_SIZE-1:0] OR_RESULT;

    // making instences for each module with seperated output 
    mov_module mov1(DATA2, MOV_RESULT);
    add_module add1(DATA1, DATA2, ADD_RESULT);
    and_module and1(DATA1, DATA2, AND_RESULT);
    or_module or1(DATA1, DATA2, OR_RESULT);

    // always block * to run the block whenever any input changes  
    always @(*)
    begin
        case (SELECT) //to SELECT what to output as a mux
        3'b000: // forward
            #1 RESULT = MOV_RESULT; 
        3'b001: // add or sub
            #2 RESULT = ADD_RESULT;
        3'b010: // and
            #1 RESULT = AND_RESULT;
        3'b011: // or
            #1 RESULT = OR_RESULT;
        //default: 3'b1xx is reserved        
        
        endcase
    end 
endmodule

Lab06/CPU Programming Tools-20240416/cpu.v
`include "alu.v"
`include "reg_file.v"

`define REG_ADDRESS_SIZE 3
`define REG_SIZE 8
`define OPCODE_SIZE 8
`define SH_AMT_SIZE 5
`define FUNC_SIZE 6
`define IMMIDIATE_SIZE 8
`define ADDRESS_SIZE 26

`define OPCODE_END 24
`define REGISTER_1_END 8
`define REGISTER_2_END 0
`define REGISTER_DEST_END 16

`define SH_AMT_END 6
`define FUNC_END 0
`define IMMIDIATE_END 0
`define ADDRESS_END 0
`define ALU_OP_SIZE 3


module mux_module(DATA1,DATA2,RESULT,SELECT);
    input [`REG_SIZE-1:0] DATA1;
    input [`REG_SIZE-1:0] DATA2;
    output reg [`REG_SIZE-1:0] RESULT; // if we want to use wire insted of reg , we woud have to use 'assign' to do that use internal_RESULT and assign to RESULT at the end
    input SELECT;

    always @(*) begin
        RESULT = SELECT ? DATA2 : DATA1;
    end

endmodule

module twos_complement(DATA,RESULT);
    input [`REG_SIZE-1:0] DATA;
    output reg [`REG_SIZE-1:0] RESULT;

    always @(DATA) begin
        #1 RESULT = ~DATA + 1'b1;
    end

endmodule


module programme_counter(RESULT,RESET,CLK);
    output reg [31:0] RESULT; 
    input RESET;
    input CLK;

    initial begin
        RESULT <= 32'd0;
    end

    always @(posedge CLK) begin
        #1
        if (RESET) begin
            RESULT <= 32'd0;
        end

        else begin
            RESULT <= RESULT + 32'd4;
        end
    end
    
endmodule



module instruction_decoder(INSTRUCTION,OPCODE,REGISTER_1,REGISTER_2,REGISTER_DEST,IMMIDIATE);           //(INSTRUCTION,OPCODE,REGISTER_1,REGISTER_2,REGISTER_DEST,SH_AMT,FUNC,IMMIDIATE,ADDRESS);
    input [31:0] INSTRUCTION;
    output reg [`OPCODE_SIZE-1:0] OPCODE;
    output reg [`REG_ADDRESS_SIZE-1:0] REGISTER_1,REGISTER_2,REGISTER_DEST;
    // output reg [`SH_AMT_SIZE-1:0] SH_AMT;
    // output reg [`FUNC_SIZE-1:0] FUNC;
    output reg [`IMMIDIATE_SIZE-1:0] IMMIDIATE;
    // output reg [`ADDRESS_SIZE-1:0] ADDRESS;

    always @(INSTRUCTION) begin
        #1
        OPCODE = INSTRUCTION[`OPCODE_END + `OPCODE_SIZE : `OPCODE_END];
        REGISTER_1 = INSTRUCTION[`REGISTER_1_END + `REG_SIZE : `REGISTER_1_END];
        REGISTER_2 = INSTRUCTION[`REGISTER_2_END + `REG_SIZE : `REGISTER_2_END];
        REGISTER_DEST = INSTRUCTION[`REGISTER_DEST_END + `REG_SIZE : `REGISTER_DEST_END];
        // SH_AMT = INSTRUCTION[`SH_AMT_END + `SH_AMT_SIZE : `SH_AMT_END];
        // FUNC = INSTRUCTION[`FUNC_END + `FUNC_SIZE : `FUNC_END];
        IMMIDIATE = INSTRUCTION[`IMMIDIATE_END + `IMMIDIATE_SIZE : `IMMIDIATE_END];
        // ADDRESS = INSTRUCTION[`ADDRESS_END + `ADDRESS_SIZE : `ADDRESS_END];
    end

endmodule


// add, sub, and, or, mov, loadi
module control_unit(OPCODE,ALU_OP,ALU_SRC,REG_WRITE,TWOS_COMP);
    input [`OPCODE_SIZE-1:0] OPCODE;
    output reg REG_DEST,MEM_READ,MEM_TO_REG,MEM_WRITE,ALU_SRC,REG_WRITE,TWOS_COMP;
    output reg [`ALU_OP_SIZE-1:0] ALU_OP;

    // always block * to run the block whenever any input changes  
    always @(*)
    begin
        case (OPCODE) 
        8'b00000000: // loadi
        begin
            // REG_DEST = 1'b0;
            // JUMP = 1'b0;
            // BRANCH = 1'b0;
            // MEM_READ = 1'b0;
            // MEM_TO_REG = 1'b1;
            ALU_OP = 3'b000; //ALUOP COMMAND
            TWOS_COMP = 1'b0;
            // MEM_WRITE = 1'b0;
            ALU_SRC = 1'b1;
            REG_WRITE = 1'b0;
        end
        8'b00000001: // mov
        begin
            // REG_DEST = 1'b1;
            // JUMP = 1'b0;
            // BRANCH = 1'b0;
            // MEM_READ = 1'b0;
            // MEM_TO_REG = 1'b0;
            ALU_OP = 3'b000; //ALUOP COMMAND
            TWOS_COMP = 1'b0;
            // MEM_WRITE = 1'b0;
            ALU_SRC = 1'b0;
            REG_WRITE = 1'b1;     
        end   
        8'b00000010: // add
        begin
            // REG_DEST = 1'b1;
            // JUMP = 1'b0;
            // BRANCH = 1'b0;
            // MEM_READ = 1'b0;
            // MEM_TO_REG = 1'b0;
            ALU_OP = 3'b001; //ALUOP COMMAND
            TWOS_COMP = 1'b0;
            // MEM_WRITE = 1'b0;
            ALU_SRC = 1'b0;
            REG_WRITE = 1'b1;   
        end
        8'b00000011: // sub
        begin
            // REG_DEST = 1'b1;
            // JUMP = 1'b0;
            // BRANCH = 1'b0;
            // MEM_READ = 1'b0;
            // MEM_TO_REG = 1'b0;
            ALU_OP = 3'b001; //ALUOP COMMAND
            TWOS_COMP = 1'b1;
            // MEM_WRITE = 1'b0;
            ALU_SRC = 1'b0;
            REG_WRITE = 1'b1;   
        end
        8'b00000100: // and
        begin
            // REG_DEST = 1'b1;
            // JUMP = 1'b0;
            // BRANCH = 1'b0;
            // MEM_READ = 1'b0;
            // MEM_TO_REG = 1'b0;
            ALU_OP = 3'b010; //ALUOP COMMAND
            TWOS_COMP = 1'b0;
            // MEM_WRITE = 1'b0;
            ALU_SRC = 1'b0;
            REG_WRITE = 1'b1;  
        end  
        8'b00000101: // or
        begin
            // REG_DEST = 1'b0;
            // JUMP = 1'b0;
            // BRANCH = 1'b0;
            // MEM_READ = 1'b0;
            // MEM_TO_REG = 1'b1;
            ALU_OP = 3'b011; //ALUOP COMMAND
            TWOS_COMP = 1'b0;
            // MEM_WRITE = 1'b0;
            ALU_SRC = 1'b0;
            REG_WRITE = 1'b0;   
        end  
        //default: 3'b1xx is reserved        

	// char *op_loadi 	= "00000000";
	// char *op_mov 	= "00000001";
	// char *op_add 	= "00000010";
	// char *op_sub 	= "00000011";
	// char *op_and 	= "00000100";
	// char *op_or 	    = "00000101";
	// char *op_j		= "00000110";
	// char *op_beq	    = "00000111";
	// char *op_lwd 	= "00001000";
	// char *op_lwi 	= "00001001";
	// char *op_swd 	= "00001010";
	// char *op_swi 	= "00001011";

        endcase
    end 

endmodule


module cpu(PCOUT, INSTRUCTION, CLK, RESET);
    input wire [31:0] INSTRUCTION;
    input wire CLK;
    input wire RESET;
    output wire [31:0] PCOUT;

    //instruction_decoder
    wire [`REG_SIZE-1:0] IMMIDIATE;
    wire [`REG_ADDRESS_SIZE-1:0] READREG2;
    wire [`REG_ADDRESS_SIZE-1:0] READREG1;
    wire [`REG_ADDRESS_SIZE-1:0] WRITEREG;
    wire [`OPCODE_SIZE-1:0] OPCODE;

    //control_unit
    wire WRITEENABLE;
    wire TWOS_COMP_SELECT;
    wire IMMIDIATE_SELECT;
    wire [`ALU_OP_SIZE-1:0] ALUOP;

    //register_file
    wire [`REG_SIZE-1:0] REGOUT2;
    wire [`REG_SIZE-1:0] REGOUT1;

    //twos_compliment
    wire [`REG_SIZE-1:0] TWOS_COMP;

    //mux
    wire [`REG_SIZE-1:0] TWOS_COMP_SELECTED;
    wire [`REG_SIZE-1:0] IMMIDIATE_SELECTED;
    // wire [`REG_ADDRESS_SIZE-1:0] SELECTED_WRITEREG;

    //alu
    wire [`REG_SIZE-1:0] ALURESULT;

    programme_counter pc(PCOUT,RESET,CLK);
    instruction_decoder instruction_decoder(INSTRUCTION,OPCODE,READREG1,READREG2,WRITEREG,IMMIDIATE);
    control_unit control_unit(OPCODE,ALUOP,IMMIDIATE_SELECT,WRITEENABLE,TWOS_COMP_SELECT);

    // mux_module write_reg_selector(READREG2,IMMIDIATE,ALUMUXOUT,ALUINMUX);
    reg_file reg_file(ALURESULT,REGOUT1,REGOUT2,WRITEREG,READREG1,READREG2,WRITEENABLE,CLK,RESET);
    twos_complement twoscomp(REGOUT2,TWOS_COMP);
    mux_module twos_complement_mux(REGOUT2,TWOS_COMP,TWOS_COMP_SELECTED,TWOS_COMP_SELECT);
    mux_module alu_immidiate_mux(TWOS_COMP_SELECTED,IMMIDIATE,IMMIDIATE_SELECTED,IMMIDIATE_SELECT);
    alu alu(REGOUT1,IMMIDIATE_SELECTED,ALURESULT,ALUOP);



endmodule

Lab06/CPU Programming Tools-20240416/reg_file.v
`define REG_ADDRESS_SIZE 3
`define REG_SIZE 8

module reg_file(IN,OUT1,OUT2,INADDRESS,OUT1ADDRESS,OUT2ADDRESS, WRITE, CLK, RESET);
    input [`REG_SIZE-1:0] IN;
    input [`REG_ADDRESS_SIZE-1:0] OUT1ADDRESS, OUT2ADDRESS, INADDRESS;
    output [`REG_SIZE-1:0] OUT1, OUT2;
    input WRITE, CLK, RESET;

    // Internal register array
    reg [`REG_SIZE-1:0] registers[`REG_SIZE-1:0];

    // Output register (registers required since we cant assign if not registers)
    reg [`REG_SIZE-1:0] out1_reg;
    reg [`REG_SIZE-1:0] out2_reg;

    // Assign outputs to internal latches
    assign OUT1 = out1_reg;         
    assign OUT2 = out2_reg;
    
    always @(posedge CLK)
    begin
        if (RESET) // If reset is high
        begin
            // Reset all registers to 0 with time delay of #1
            registers[0] <= #1 8'b0;
            registers[1] <= #1 8'b0;
            registers[2] <= #1 8'b0;
            registers[3] <= #1 8'b0;
            registers[4] <= #1 8'b0;
            registers[5] <= #1 8'b0;
            registers[6] <= #1 8'b0;
            registers[7] <= #1 8'b0;
        end
        
        else if (WRITE) // If write is high
        begin
            registers[INADDRESS] <= #1 IN; // #1 propergation delay
        end
        
        else  // Else times output should be what ever address the pointers are pointing at
        begin   // Outputting values with #2 delay 
            out1_reg <= #2 registers[OUT1ADDRESS];      //here registers are reqired , since wirescant be used to store values
            out2_reg <= #2 registers[OUT2ADDRESS];
        end

    end

endmodule

Lab06/CPU Programming Tools-20240416/cpu_tb2.v
/*
    * CO224 - Computer Architecture
    * Lab 05 - Part 3
    * reg_file module
    * Version 1.0
*/

`include "cpu.v"

module Testbench;
    reg CLK, RESET;
    wire [31:0] PC;
    reg [31:0] INSTRUCTION;

    cpu mycpu(PC, INSTRUCTION, CLK, RESET);

    always @ (PC)
    begin
        # 2 // Latency for instruction register
        // Manually written opcodes
        case (PC)
            32'b0000_0000_0000_0000_0000_0000_0000_0000: INSTRUCTION = 32'b00000000_00000100_00000000_00000101; // loadi 4 0x05
            
            32'b0000_0000_0000_0000_0000_0000_0000_0100: INSTRUCTION = 32'b00000000_00000010_00000000_00001001; // loadi 2 0x09

            32'b0000_0000_0000_0000_0000_0000_0000_1000: INSTRUCTION = 32'b00000010_00000110_00000100_00000010; // add 6 4 2

            32'b0000_0000_0000_0000_0000_0000_0000_1100: INSTRUCTION = 32'b00000001_00000000_00000000_00000110; // mov 0 6
            
            32'b0000_0000_0000_0000_0000_0000_0001_0000: INSTRUCTION = 32'b00000000_00000001_00000000_00000001; // loadi 1 0x01
            
            32'b0000_0000_0000_0000_0000_0000_0001_0100: INSTRUCTION = 32'b00000010_00000010_00000010_00000001; // add 2 2 1
        endcase
    end

    initial begin
        // generate files needed to plot the waveform using GTKWave
        $dumpfile("cpu_wavedata.vcd");
		$dumpvars(0, mycpu);
        
        
        RESET = 1'b0;
        CLK = 1'b0;
        
        // TODO: Reset the CPU (by giving a pulse to RESET signal) to start the program execution
        RESET = 1;
        #6
        RESET = 0;
        // finish simulation after some time
        #100
        $finish;
    end
        
    
    // clock signal generation
    always
        #4 CLK = ~CLK;
    
endmodule

Lab06/CPU Programming Tools-20240416/cpu_wavedata.vcd
$date
	Wed Apr 24 15:14:51 2024
$end
$version
	Icarus Verilog
$end
$timescale
	1s
$end
$scope module Testbench $end
$scope module mycpu $end
$var wire 1 ! CLK $end
$var wire 32 " INSTRUCTION [31:0] $end
$var wire 1 # RESET $end
$var wire 3 $ WRITEREG [2:0] $end
$var wire 1 % WRITEENABLE $end
$var wire 8 & TWOS_COMP_SELECTED [7:0] $end
$var wire 1 ' TWOS_COMP_SELECT $end
$var wire 8 ( TWOS_COMP [7:0] $end
$var wire 8 ) REGOUT2 [7:0] $end
$var wire 8 * REGOUT1 [7:0] $end
$var wire 3 + READREG2 [2:0] $end
$var wire 3 , READREG1 [2:0] $end
$var wire 32 - PCOUT [31:0] $end
$var wire 8 . OPCODE [7:0] $end
$var wire 8 / IMMIDIATE_SELECTED [7:0] $end
$var wire 1 0 IMMIDIATE_SELECT $end
$var wire 8 1 IMMIDIATE [7:0] $end
$var wire 8 2 ALURESULT [7:0] $end
$var wire 3 3 ALUOP [2:0] $end
$scope module alu $end
$var wire 3 4 SELECT [2:0] $end
$var wire 8 5 OR_RESULT [7:0] $end
$var wire 8 6 MOV_RESULT [7:0] $end
$var wire 8 7 DATA2 [7:0] $end
$var wire 8 8 DATA1 [7:0] $end
$var wire 8 9 AND_RESULT [7:0] $end
$var wire 8 : ADD_RESULT [7:0] $end
$var reg 8 ; RESULT [7:0] $end
$scope module add1 $end
$var wire 8 < DATA2 [7:0] $end
$var wire 8 = DATA1 [7:0] $end
$var reg 8 > RESULT [7:0] $end
$upscope $end
$scope module and1 $end
$var wire 8 ? RESULT [7:0] $end
$var wire 8 @ DATA2 [7:0] $end
$var wire 8 A DATA1 [7:0] $end
$upscope $end
$scope module mov1 $end
$var wire 8 B RESULT [7:0] $end
$var wire 8 C DATA2 [7:0] $end
$upscope $end
$scope module or1 $end
$var wire 8 D RESULT [7:0] $end
$var wire 8 E DATA2 [7:0] $end
$var wire 8 F DATA1 [7:0] $end
$upscope $end
$upscope $end
$scope module alu_immidiate_mux $end
$var wire 1 0 SELECT $end
$var wire 8 G DATA2 [7:0] $end
$var wire 8 H DATA1 [7:0] $end
$var reg 8 I RESULT [7:0] $end
$upscope $end
$scope module control_unit $end
$var wire 8 J OPCODE [7:0] $end
$var reg 3 K ALU_OP [2:0] $end
$var reg 1 0 ALU_SRC $end
$var reg 1 L MEM_READ $end
$var reg 1 M MEM_TO_REG $end
$var reg 1 N MEM_WRITE $end
$var reg 1 O REG_DEST $end
$var reg 1 % REG_WRITE $end
$var reg 1 ' TWOS_COMP $end
$upscope $end
$scope module instruction_decoder $end
$var wire 32 P INSTRUCTION [31:0] $end
$var reg 8 Q IMMIDIATE [7:0] $end
$var reg 8 R OPCODE [7:0] $end
$var reg 3 S REGISTER_1 [2:0] $end
$var reg 3 T REGISTER_2 [2:0] $end
$var reg 3 U REGISTER_DEST [2:0] $end
$upscope $end
$scope module pc $end
$var wire 1 ! CLK $end
$var wire 1 # RESET $end
$var reg 32 V RESULT [31:0] $end
$upscope $end
$scope module reg_file $end
$var wire 1 ! CLK $end
$var wire 8 W IN [7:0] $end
$var wire 3 X INADDRESS [2:0] $end
$var wire 3 Y OUT1ADDRESS [2:0] $end
$var wire 8 Z OUT2 [7:0] $end
$var wire 3 [ OUT2ADDRESS [2:0] $end
$var wire 1 # RESET $end
$var wire 1 % WRITE $end
$var wire 8 \ OUT1 [7:0] $end
$var reg 8 ] out1_reg [7:0] $end
$var reg 8 ^ out2_reg [7:0] $end
$upscope $end
$scope module twos_complement_mux $end
$var wire 8 _ DATA1 [7:0] $end
$var wire 1 ' SELECT $end
$var wire 8 ` DATA2 [7:0] $end
$var reg 8 a RESULT [7:0] $end
$upscope $end
$scope module twoscomp $end
$var wire 8 b DATA [7:0] $end
$var reg 8 c RESULT [7:0] $end
$upscope $end
$upscope $end
$upscope $end
$enddefinitions $end
$comment Show the parameter values. $end
$dumpall
$end
#0
$dumpvars
bx c
bx b
bx a
bx `
bx _
bx ^
bx ]
bx \
bx [
bx Z
bx Y
bx X
bx W
b0 V
bx U
bx T
bx S
bx R
bx Q
bx P
xO
xN
xM
xL
bx K
bx J
bx I
bx H
bx G
bx F
bx E
bx D
bx C
bx B
bx A
bx @
bx ?
bx >
bx =
bx <
bx ;
bx :
bx 9
bx 8
bx 7
bx 6
bx 5
bx 4
bx 3
bx 2
bx 1
x0
bx /
bx .
b0 -
bx ,
bx +
bx *
bx )
bx (
x'
bx &
x%
bx $
1#
bx "
0!
$end
#2
b1000000000000000101 "
b1000000000000000101 P
#3
bx1x1 5
bx1x1 D
b0x0x 9
b0x0x ?
b101 6
b101 B
b101 /
b101 7
b101 <
b101 @
b101 C
b101 E
b101 I
0%
10
0'
b0 3
b0 4
b0 K
b101 1
b101 G
b101 Q
b100 $
b100 U
b100 X
b101 +
b101 T
b101 [
b0 ,
b0 S
b0 Y
b0 .
b0 J
b0 R
#4
b101 2
b101 ;
b101 W
1!
#6
0#
#8
0!
#12
1!
#13
b100 -
b100 V
#14
b0 &
b0 H
b0 a
b101 5
b101 D
b0 9
b0 ?
b101 :
b101 >
b0 )
b0 Z
b0 _
b0 b
b0 ^
b0 *
b0 8
b0 =
b0 A
b0 F
b0 \
b0 ]
#15
b0 (
b0 `
b0 c
b100000000000001001 "
b100000000000001001 P
#16
b1001 5
b1001 D
b1001 :
b1001 >
b1001 6
b1001 B
b1001 /
b1001 7
b1001 <
b1001 @
b1001 C
b1001 E
b1001 I
b1001 1
b1001 G
b1001 Q
b10 $
b10 U
b10 X
b1 +
b1 T
b1 [
0!
#17
b1001 2
b1001 ;
b1001 W
#20
1!
#21
b1000 -
b1000 V
#23
b10000001100000010000000010 "
b10000001100000010000000010 P
#24
b0 5
b0 D
b0 :
b0 >
b0 6
b0 B
b0 /
b0 7
b0 <
b0 @
b0 C
b0 E
b0 I
1%
00
b1 3
b1 4
b1 K
b10 1
b10 G
b10 Q
b110 $
b110 U
b110 X
b10 +
b10 T
b10 [
b100 ,
b100 S
b100 Y
b10 .
b10 J
b10 R
0!
#26
b0 2
b0 ;
b0 W
#28
1!
#29
b1100 -
b1100 V
#31
b1000000000000000000000110 "
b1000000000000000000000110 P
#32
b0 3
b0 4
b0 K
b110 1
b110 G
b110 Q
b0 $
b0 U
b0 X
b110 +
b110 T
b110 [
b0 ,
b0 S
b0 Y
b1 .
b1 J
b1 R
0!
#36
1!
#37
b10000 -
b10000 V
#39
b10000000000000001 "
b10000000000000001 P
#40
b1 5
b1 D
b1 :
b1 >
b1 6
b1 B
b1 /
b1 7
b1 <
b1 @
b1 C
b1 E
b1 I
0%
10
b1 1
b1 G
b1 Q
b1 $
b1 U
b1 X
b1 +
b1 T
b1 [
b0 .
b0 J
b0 R
0!
#41
b1 2
b1 ;
b1 W
#44
1!
#45
b10100 -
b10100 V
#47
b10000000100000001000000001 "
b10000000100000001000000001 P
#48
b0 5
b0 D
b0 :
b0 >
b0 6
b0 B
b0 /
b0 7
b0 <
b0 @
b0 C
b0 E
b0 I
1%
00
b1 3
b1 4
b1 K
b10 $
b10 U
b10 X
b10 ,
b10 S
b10 Y
b10 .
b10 J
b10 R
0!
#50
b0 2
b0 ;
b0 W
#52
1!
#53
b11000 -
b11000 V
#56
0!
#60
1!
#61
b11100 -
b11100 V
#64
0!
#68
1!
#69
b100000 -
b100000 V
#72
0!
#76
1!
#77
b100100 -
b100100 V
#80
0!
#84
1!
#85
b101000 -
b101000 V
#88
0!
#92
1!
#93
b101100 -
b101100 V
#96
0!
#100
1!
#101
b110000 -
b110000 V
