Lab06/CPU Programming Tools-20240416/alu.v
`define REG_SIZE 8
`define REG_ADDRESS_SIZE 3


module mov_module (DATA2,RESULT);
    input [`REG_SIZE-1:0] DATA2;
    output [`REG_SIZE-1:0] RESULT;

    assign RESULT = DATA2;

endmodule

module add_module (DATA1,DATA2,RESULT);
    input [`REG_SIZE-1:0] DATA1;
    input [`REG_SIZE-1:0] DATA2;
    output reg [`REG_SIZE-1:0] RESULT;
    
    always @(*) 
    begin   // add - sub
    if (DATA2 < 0)  // or we can use (DATA2[7]) as the condition
        RESULT = DATA1 - DATA2;
    else
        RESULT = DATA1 + DATA2;
    end

endmodule

module and_module (DATA1,DATA2,RESULT);
    input [`REG_SIZE-1:0] DATA1;
    input [`REG_SIZE-1:0] DATA2;
    output [`REG_SIZE-1:0] RESULT;

    assign RESULT = DATA1 & DATA2;

endmodule

module or_module (DATA1,DATA2,RESULT);
    input [`REG_SIZE-1:0] DATA1;
    input [`REG_SIZE-1:0] DATA2;
    output [`REG_SIZE-1:0] RESULT;

    assign RESULT = DATA1 | DATA2;


endmodule

module alu (DATA1,DATA2,RESULT,SELECT,ZERO);
    input [`REG_SIZE-1:0] DATA1;
    input [`REG_SIZE-1:0] DATA2;
    output reg [`REG_SIZE-1:0] RESULT; // if we want to use wire insted of reg , we woud have to use 'assign' to do that use internal_RESULT and assign to RESULT at the end
    input [`REG_ADDRESS_SIZE-1:0] SELECT;
    output reg ZERO;

    // making wires to have each module's answer.
    wire [`REG_SIZE-1:0] MOV_RESULT;     
    wire [`REG_SIZE-1:0] ADD_RESULT;
    wire [`REG_SIZE-1:0] AND_RESULT;
    wire [`REG_SIZE-1:0] OR_RESULT;

    // making instences for each module with seperated output 
    mov_module mov1(DATA2, MOV_RESULT);
    add_module add1(DATA1, DATA2, ADD_RESULT);
    and_module and1(DATA1, DATA2, AND_RESULT);
    or_module or1(DATA1, DATA2, OR_RESULT);

    // to check of result is zero for the branch if equal command
    always @(*) begin
        if (!ADD_RESULT) begin
            ZERO = 1;
        end
        else begin
            ZERO = 0;
        end
    end

    // always block * to run the block whenever any input changes  
    always @(*)
    begin
        case (SELECT) //to SELECT what to output as a mux
        3'b000: // forward
            #1 RESULT = MOV_RESULT; 
        3'b001: // add or sub
            #2 RESULT = ADD_RESULT;
        3'b010: // and
            #1 RESULT = AND_RESULT;
        3'b011: // or
            #1 RESULT = OR_RESULT;
        //default: 3'b1xx is reserved        
        
        endcase
    end 
endmodule

Lab06/CPU Programming Tools-20240416/cpu.v
`include "alu.v"
`include "reg_file.v"

// Variables defined if have to change later(No effect when synthesising since all replace by it's value)
`define REG_ADDRESS_SIZE 3
`define REG_SIZE 8
`define OPCODE_SIZE 8
`define SH_AMT_SIZE 5
`define FUNC_SIZE 6
`define IMMIDIATE_SIZE 8
`define ADDRESS_SIZE 26
`define JUMP_SIZE 8


`define OPCODE_END 24
`define REGISTER_1_END 8
`define REGISTER_2_END 0
`define REGISTER_DEST_END 16

`define SH_AMT_END 6
`define FUNC_END 0
`define IMMIDIATE_END 0
`define ADDRESS_END 0
`define BRANCH_END 16
`define JUMP_END 16

`define ALU_OP_SIZE 3



// Module for size 8 mux
module mux_module8(DATA1,DATA2,RESULT,SELECT);
    input [`REG_SIZE-1:0] DATA1;
    input [`REG_SIZE-1:0] DATA2;
    output reg [`REG_SIZE-1:0] RESULT; // if we want to use wire insted of reg , we woud have to use 'assign' to do that use internal_RESULT and assign to RESULT at the end
    input SELECT;

    always @(*) begin // Selecting
        RESULT = SELECT ? DATA2 : DATA1;
    end

endmodule

// Module for size 32 mux
module mux_module32(DATA1,DATA2,RESULT,SELECT);
    input [31:0] DATA1;
    input [31:0] DATA2;
    output reg [31:0] RESULT; // if we want to use wire insted of reg , we woud have to use 'assign' to do that use internal_RESULT and assign to RESULT at the end
    input SELECT;

    always @(*) begin // Selecting
        RESULT = SELECT ? DATA2 : DATA1;
    end

endmodule

// Module for Two's complement
module twos_complement(DATA,RESULT);
    input [`REG_SIZE-1:0] DATA;
    output reg [`REG_SIZE-1:0] RESULT;

    always @(DATA) begin
        #1 RESULT = ~DATA + 1'b1; // Convering to the two's complement
    end

endmodule

// Programme counter module
module programme_counter(PCOUT,NEXTPCOUT,RESET,CLK,SELECTEDOUTPUT);
    output reg [31:0] PCOUT; 
    output reg [31:0] NEXTPCOUT; 
    input [31:0] SELECTEDOUTPUT;
    input RESET;
    input CLK;

    always @(posedge CLK) begin
        if (RESET) begin // Sets to zero of resset is  high
            PCOUT <= #1 32'b0000_0000_0000_0000_0000_0000;
            NEXTPCOUT <= #2 32'b0000_0000_0000_0000_0000_0100;
        end

        else begin // incrementing
            PCOUT <= #1 SELECTEDOUTPUT;
            NEXTPCOUT <= #2 SELECTEDOUTPUT + 32'd4;
        end
    end
    
endmodule


// Module for decoding instructions
module instruction_decoder(INSTRUCTION,OPCODE,REGISTER_1,REGISTER_2,REGISTER_DEST,IMMIDIATE,BRANCHADDRESS,JUMPADDRESS);
    input [31:0] INSTRUCTION;
    output reg [`OPCODE_SIZE-1:0] OPCODE;
    output reg [`REG_ADDRESS_SIZE-1:0] REGISTER_1,REGISTER_2,REGISTER_DEST;
    output reg [`IMMIDIATE_SIZE-1:0] IMMIDIATE;
    output reg [`JUMP_SIZE-1:0] JUMPADDRESS;
    output reg [`IMMIDIATE_SIZE-1:0] BRANCHADDRESS;

    always @(INSTRUCTION) begin
        OPCODE = INSTRUCTION[`OPCODE_END + `OPCODE_SIZE : `OPCODE_END]; 
        REGISTER_1 = INSTRUCTION[`REGISTER_1_END + `REG_SIZE : `REGISTER_1_END];
        REGISTER_2 = INSTRUCTION[`REGISTER_2_END + `REG_SIZE : `REGISTER_2_END];
        REGISTER_DEST = INSTRUCTION[`REGISTER_DEST_END + `REG_SIZE : `REGISTER_DEST_END];
        IMMIDIATE = INSTRUCTION[`IMMIDIATE_END + `IMMIDIATE_SIZE : `IMMIDIATE_END];
        BRANCHADDRESS = INSTRUCTION[`BRANCH_END + `IMMIDIATE_SIZE : `BRANCH_END];
        JUMPADDRESS = INSTRUCTION[`JUMP_END + `JUMP_SIZE : `JUMP_END];
    end

endmodule

// sign_extender
module sign_extender(INPUT,OUTPUT);
    input [`JUMP_SIZE-1:0] INPUT;
    output reg [31:0] OUTPUT;

    always @(INPUT) begin
        if (INPUT[7]) begin
            OUTPUT [31:`JUMP_SIZE] = 24'b1111_1111_1111_1111_1111_1111;
        end
        else begin
            OUTPUT [31:`JUMP_SIZE] = 24'b0000_0000_0000_0000_0000_0000;
        end
        OUTPUT [`JUMP_SIZE-1:0] = INPUT;
    end

endmodule

// left shift module
module left_shift(INPUT,OUTPUT);
    input [31:0] INPUT;
    output reg [31:0] OUTPUT;

    always @(INPUT) begin
        OUTPUT[31:2] = INPUT[29:0];
        OUTPUT[1:0] = 2'b00;
    end

endmodule

// jump_concatenate
module jump_concatenate(PCOUT,LEFTSHIFTEDJUMP,JUMPADDRESS);
    input [31:0] PCOUT;
    input [31:0] LEFTSHIFTEDJUMP;
    output reg [31:0] JUMPADDRESS;

    always @(PCOUT,LEFTSHIFTEDJUMP) begin
        JUMPADDRESS = PCOUT + LEFTSHIFTEDJUMP;
    end

endmodule

// and module for branch if equal instruction
module branch_and(DATA1,DATA2,RESULT);
    input DATA1;
    input DATA2;
    output RESULT;

    assign RESULT = DATA1 & DATA2;

endmodule

// add module for branch if equal instruction
module branch_add(PCOUT,LEFTSHIFTEDBRANCH,BRANCHADDRESS);
    input [31:0] PCOUT;
    input [31:0] LEFTSHIFTEDBRANCH;
    output reg [31:0] BRANCHADDRESS;

    always @(PCOUT,LEFTSHIFTEDBRANCH) begin
        BRANCHADDRESS = PCOUT + LEFTSHIFTEDBRANCH;
    end    
endmodule

// add, sub, and, or, mov, loadi
module control_unit(OPCODE,ALU_OP,ALU_SRC,REG_WRITE,TWOS_COMP,BRANCH_SELECT,JUMP_SELECT);
    input [`OPCODE_SIZE-1:0] OPCODE;
    output reg ALU_SRC,REG_WRITE,TWOS_COMP,BRANCH_SELECT,JUMP_SELECT;
    output reg [`ALU_OP_SIZE-1:0] ALU_OP;

    // always block * to run the block whenever any input changes  
    always @(*)
    begin
        #1 // Decorder delay
        case (OPCODE) 
        8'b00000000: // loadi
        begin
            ALU_OP = 3'b000; //ALUOP COMMAND
            TWOS_COMP = 1'b0;
            ALU_SRC = 1'b1;
            REG_WRITE = 1'b1;
            BRANCH_SELECT = 1'b0;
            JUMP_SELECT = 1'b0;
        end
        8'b00000001: // mov
        begin
            ALU_OP = 3'b000; //ALUOP COMMAND
            TWOS_COMP = 1'b0;
            ALU_SRC = 1'b0;
            REG_WRITE = 1'b1;
            BRANCH_SELECT = 1'b0;
            JUMP_SELECT = 1'b0;     
        end   
        8'b00000010: // add
        begin
            ALU_OP = 3'b001; //ALUOP COMMAND
            TWOS_COMP = 1'b0;
            ALU_SRC = 1'b0;
            REG_WRITE = 1'b1;
            BRANCH_SELECT = 1'b0;
            JUMP_SELECT = 1'b0;   
        end
        8'b00000011: // sub
        begin
            ALU_OP = 3'b001; //ALUOP COMMAND
            TWOS_COMP = 1'b1;
            ALU_SRC = 1'b0;
            REG_WRITE = 1'b1;
            BRANCH_SELECT = 1'b0;
            JUMP_SELECT = 1'b0;  
        end
        8'b00000100: // and
        begin
            ALU_OP = 3'b010; //ALUOP COMMAND
            TWOS_COMP = 1'b0;
            ALU_SRC = 1'b0;
            REG_WRITE = 1'b1;
            BRANCH_SELECT = 1'b0;
            JUMP_SELECT = 1'b0; 
        end  
        8'b00000101: // or
        begin
            ALU_OP = 3'b011; //ALUOP COMMAND
            TWOS_COMP = 1'b0;
            ALU_SRC = 1'b0;
            REG_WRITE = 1'b1; 
            BRANCH_SELECT = 1'b0;
            JUMP_SELECT = 1'b0;  
        end   
        8'b00000110: // j 
        begin
            ALU_OP = 3'b000; //ALUOP COMMAND
            TWOS_COMP = 1'b0;
            ALU_SRC = 1'b0;
            REG_WRITE = 1'b0; 
            BRANCH_SELECT = 1'b0;
            JUMP_SELECT = 1'b1;  
        end  
        8'b00000111: // beq
        begin
            ALU_OP = 3'b000; //ALUOP COMMAND
            TWOS_COMP = 1'b1;
            ALU_SRC = 1'b0;
            REG_WRITE = 1'b0; 
            BRANCH_SELECT = 1'b1;
            JUMP_SELECT = 1'b0;  
        end 
        default:
        begin
            ALU_OP = 3'b000; //ALUOP COMMAND
            TWOS_COMP = 1'b0;
            ALU_SRC = 1'b0;
            REG_WRITE = 1'b0; 
            BRANCH_SELECT = 1'b0;
            JUMP_SELECT = 1'b0; 
        end
        endcase
    end 

endmodule

	// char *op_j		= "00000110";
	// char *op_beq	= "00000111";

module cpu(PCOUT, INSTRUCTION, CLK, RESET);
    input wire [31:0] INSTRUCTION;
    input wire CLK;
    input wire RESET;

    //programe counter
    output wire [31:0] PCOUT;
    output wire [31:0] NEXTPCOUT;

    //instruction_decoder
    wire [`IMMIDIATE_SIZE-1:0] IMMIDIATE;
    wire [`REG_ADDRESS_SIZE-1:0] READREG2;
    wire [`REG_ADDRESS_SIZE-1:0] READREG1;
    wire [`REG_ADDRESS_SIZE-1:0] WRITEREG;
    wire [`OPCODE_SIZE-1:0] OPCODE;
    wire [`JUMP_SIZE-1:0] JUMPINSTRUCTION;
    wire [`JUMP_SIZE-1:0] BRANCHINSTRUCTION;


    //sign_extender
    wire [31:0] SIGNEXTENDEDJUMP;
    wire [31:0] SIGNEXTENDEDBRANCH;

    //left_shift
    wire [31:0] LEFTSHIFTEDJUMP;
    wire [31:0] LEFTSHIFTEDBRANCH;

    //jump_concatenator
    wire [31:0] JUMPADDRESS;

    //branch_add
    wire [31:0] BRANCHADDRESS;

    //branch_and
    wire ZERO_and_BRANCHSELECT;

    //control_unit
    wire WRITEENABLE;
    wire TWOS_COMP_SELECT;
    wire IMMIDIATE_SELECT;
    wire [`ALU_OP_SIZE-1:0] ALUOP;
    wire BRANCH_SELECT;
    wire JUMP_SELECT;

    //register_file
    wire [`REG_SIZE-1:0] REGOUT2;
    wire [`REG_SIZE-1:0] REGOUT1;

    //twos_compliment
    wire [`REG_SIZE-1:0] TWOS_COMP;

    //mux
    wire [`REG_SIZE-1:0] TWOS_COMP_SELECTED;
    wire [`REG_SIZE-1:0] IMMIDIATE_SELECTED;
    wire [31:0] BRANCH_SELECTED;
    output wire [31:0] JUMP_SELECTED;

    //alu
    wire [`REG_SIZE-1:0] ALURESULT;
    wire ZERO;

    programme_counter pc(PCOUT,NEXTPCOUT,RESET,CLK,JUMP_SELECTED); // The programme counter
    instruction_decoder instruction_decoder(INSTRUCTION,OPCODE,READREG1,READREG2,WRITEREG,IMMIDIATE,BRANCHINSTRUCTION,JUMPINSTRUCTION);   // The instruction decorder
    
    sign_extender sign_extender_for_jump(JUMPINSTRUCTION,SIGNEXTENDEDJUMP);     // sign extend for jump instruction
    left_shift left_shift_for_jump(SIGNEXTENDEDJUMP,LEFTSHIFTEDJUMP);   // left shift for jump instruction 
    jump_concatenate jump_concatenate(NEXTPCOUT,LEFTSHIFTEDJUMP,JUMPADDRESS);   // jump concatenator

    sign_extender sign_extender_for_branch(BRANCHINSTRUCTION,SIGNEXTENDEDBRANCH);   // sign extended for branch imidiate value
    left_shift left_shift_for_branch(SIGNEXTENDEDBRANCH,LEFTSHIFTEDBRANCH); // left shift for branch iimidiate value
    branch_add branch_add(NEXTPCOUT,LEFTSHIFTEDBRANCH,BRANCHADDRESS);    // adding address to PC+4 for branch instruction

    control_unit control_unit(OPCODE,ALUOP,IMMIDIATE_SELECT,WRITEENABLE,TWOS_COMP_SELECT,BRANCH_SELECT,JUMP_SELECT);  // Control unit

    reg_file reg_file(ALURESULT,REGOUT1,REGOUT2,WRITEREG,READREG1,READREG2,WRITEENABLE,CLK,RESET);  // Register file
    twos_complement twoscomp(REGOUT2,TWOS_COMP);    // Twos complement 

    mux_module8 twos_complement_mux(REGOUT2,TWOS_COMP,TWOS_COMP_SELECTED,TWOS_COMP_SELECT);      // mux to select the two's complement
    mux_module8 alu_immidiate_mux(TWOS_COMP_SELECTED,IMMIDIATE,IMMIDIATE_SELECTED,IMMIDIATE_SELECT);     // Mux to select the immidate value from the instruction
    
    branch_and branch_and(BRANCH_SELECT,ZERO,ZERO_and_BRANCHSELECT);    // and gate for if_Zero and Branch control signal
    mux_module32 branch_select_mux(NEXTPCOUT,BRANCHADDRESS,BRANCH_SELECTED,ZERO_and_BRANCHSELECT); // selcting mux whether to branch or not

    mux_module32 jump_select_mux(BRANCH_SELECTED,JUMPADDRESS,JUMP_SELECTED,JUMP_SELECT); // selcting mux whether to branch or not

    alu alu(REGOUT1,IMMIDIATE_SELECTED,ALURESULT,ALUOP,ZERO);    // The ALU 
    // assign NEXTPCOUT = JUMP_SELECTED;

endmodule

Lab06/CPU Programming Tools-20240416/group19_lab6_part1/reg_file.v
`define REG_ADDRESS_SIZE 3 // Size of a register address
`define REG_SIZE 8 // size of a register

module reg_file(IN,OUT1,OUT2,INADDRESS,OUT1ADDRESS,OUT2ADDRESS, WRITE, CLK, RESET);
    input [`REG_SIZE-1:0] IN;
    input [`REG_ADDRESS_SIZE-1:0] OUT1ADDRESS, OUT2ADDRESS, INADDRESS;
    output [`REG_SIZE-1:0] OUT1, OUT2;
    input WRITE, CLK, RESET;

    // Internal register array
    reg [`REG_SIZE-1:0] registers[`REG_SIZE-1:0];

    // Assign outputs to internal latches
    assign #2 OUT1 = registers[OUT1ADDRESS];         
    assign #2 OUT2 = registers[OUT2ADDRESS];
    
    always @(posedge CLK)
    begin

        if (RESET) // If reset is high
        begin
            // Reset all registers to 0 with time delay of #1
            registers[0] <= #1 8'b0;
            registers[1] <= #1 8'b0;
            registers[2] <= #1 8'b0;
            registers[3] <= #1 8'b0;
            registers[4] <= #1 8'b0;
            registers[5] <= #1 8'b0;
            registers[6] <= #1 8'b0;
            registers[7] <= #1 8'b0;
        end
        
        else if (WRITE) // If write is high
        begin
            registers[INADDRESS] <= #1 IN; // #1 propergation delay
        end

    end

endmodule

Lab06/CPU Programming Tools-20240416/cpu_tb.v
// Computer Architecture (CO224) - Lab 05
// Design: Testbench of Integrated CPU of Simple Processor
// Author: Isuru Nawinne

`include "cpu.v"

module cpu_tb;

    reg CLK, RESET;
    wire [31:0] PC;
    wire [31:0] INSTRUCTION;

    
    // TODO: Initialize an array of registers (8x1024) named 'instr_mem' to be used as instruction memory
    reg [7:0] instr_mem [1023:0];
    
    // TODO: Create combinational logic to support CPU instruction fetching, given the Program Counter(PC) value 
    //       (make sure you include the delay for instruction fetching here)
    assign INSTRUCTION = {instr_mem[PC+3], instr_mem[PC+2], instr_mem[PC+1], instr_mem[PC]};
    
    initial
    begin
        // Initialize instruction memory with the set of instructions you need execute on CPU
        
        // METHOD 1: manually loading instructions to instr_mem
        // {instr_mem[10'd3], instr_mem[10'd2], instr_mem[10'd1], instr_mem[10'd0]} = 32'b00000000000001000000000000000101;
        // {instr_mem[10'd7], instr_mem[10'd6], instr_mem[10'd5], instr_mem[10'd4]} = 32'b00000000000000100000000000001001;
        // {instr_mem[10'd11], instr_mem[10'd10], instr_mem[10'd9], instr_mem[10'd8]} = 32'b00000010000001100000010000000010;
        
        // METHOD 2: loading instr_mem content from instr_mem.mem file
        $readmemb("instr_mem.mem", instr_mem,0,1023);
    end
    
    /* 
    -----
     CPU
    -----
    */
    cpu mycpu(PC, INSTRUCTION, CLK, RESET);
    
    integer i;
    initial
    begin
    
        // generate files needed to plot the waveform using GTKWave
        $dumpfile("cpu_wavedata.vcd");
		$dumpvars(0, cpu_tb);
        
        for (i=0 ;i<8;i=i+1)
            $dumpvars(1,cpu_tb.mycpu.reg_file.registers[i]);
        
        CLK = 1'b0;
        RESET = 1'b0;
        
        // TODO: Reset the CPU (by giving a pulse to RESET signal) to start the program execution
        RESET = 1'b1;
        #6
        RESET = 1'b0;
        
        // finish simulation after some time
        #500
        $finish;
        
    end
    
    // clock signal generation
    always
        #4 CLK = ~CLK;
        

endmodule

Lab06/CPU Programming Tools-20240416/cpu_wavedata.vcd
$date
	Tue May 14 16:18:39 2024
$end
$version
	Icarus Verilog
$end
$timescale
	1s
$end
$scope module cpu_tb $end
$var wire 32 ! PC [31:0] $end
$var wire 32 " INSTRUCTION [31:0] $end
$var reg 1 # CLK $end
$var reg 1 $ RESET $end
$var integer 32 % i [31:0] $end
$scope module mycpu $end
$var wire 1 # CLK $end
$var wire 32 & INSTRUCTION [31:0] $end
$var wire 1 $ RESET $end
$var wire 1 ' ZERO_and_BRANCHSELECT $end
$var wire 1 ( ZERO $end
$var wire 3 ) WRITEREG [2:0] $end
$var wire 1 * WRITEENABLE $end
$var wire 8 + TWOS_COMP_SELECTED [7:0] $end
$var wire 1 , TWOS_COMP_SELECT $end
$var wire 8 - TWOS_COMP [7:0] $end
$var wire 32 . SIGNEXTENDEDJUMP [31:0] $end
$var wire 32 / SIGNEXTENDEDBRANCH [31:0] $end
$var wire 8 0 REGOUT2 [7:0] $end
$var wire 8 1 REGOUT1 [7:0] $end
$var wire 3 2 READREG2 [2:0] $end
$var wire 3 3 READREG1 [2:0] $end
$var wire 32 4 PCOUT [31:0] $end
$var wire 8 5 OPCODE [7:0] $end
$var wire 32 6 NEXTPCOUT [31:0] $end
$var wire 32 7 LEFTSHIFTEDJUMP [31:0] $end
$var wire 32 8 LEFTSHIFTEDBRANCH [31:0] $end
$var wire 32 9 JUMP_SELECTED [31:0] $end
$var wire 1 : JUMP_SELECT $end
$var wire 8 ; JUMPINSTRUCTION [7:0] $end
$var wire 32 < JUMPADDRESS [31:0] $end
$var wire 8 = IMMIDIATE_SELECTED [7:0] $end
$var wire 1 > IMMIDIATE_SELECT $end
$var wire 8 ? IMMIDIATE [7:0] $end
$var wire 32 @ BRANCH_SELECTED [31:0] $end
$var wire 1 A BRANCH_SELECT $end
$var wire 8 B BRANCHINSTRUCTION [7:0] $end
$var wire 32 C BRANCHADDRESS [31:0] $end
$var wire 8 D ALURESULT [7:0] $end
$var wire 3 E ALUOP [2:0] $end
$scope module alu $end
$var wire 3 F SELECT [2:0] $end
$var wire 8 G OR_RESULT [7:0] $end
$var wire 8 H MOV_RESULT [7:0] $end
$var wire 8 I DATA2 [7:0] $end
$var wire 8 J DATA1 [7:0] $end
$var wire 8 K AND_RESULT [7:0] $end
$var wire 8 L ADD_RESULT [7:0] $end
$var reg 8 M RESULT [7:0] $end
$var reg 1 ( ZERO $end
$scope module add1 $end
$var wire 8 N DATA2 [7:0] $end
$var wire 8 O DATA1 [7:0] $end
$var reg 8 P RESULT [7:0] $end
$upscope $end
$scope module and1 $end
$var wire 8 Q RESULT [7:0] $end
$var wire 8 R DATA2 [7:0] $end
$var wire 8 S DATA1 [7:0] $end
$upscope $end
$scope module mov1 $end
$var wire 8 T RESULT [7:0] $end
$var wire 8 U DATA2 [7:0] $end
$upscope $end
$scope module or1 $end
$var wire 8 V RESULT [7:0] $end
$var wire 8 W DATA2 [7:0] $end
$var wire 8 X DATA1 [7:0] $end
$upscope $end
$upscope $end
$scope module alu_immidiate_mux $end
$var wire 1 > SELECT $end
$var wire 8 Y DATA2 [7:0] $end
$var wire 8 Z DATA1 [7:0] $end
$var reg 8 [ RESULT [7:0] $end
$upscope $end
$scope module branch_add $end
$var wire 32 \ PCOUT [31:0] $end
$var wire 32 ] LEFTSHIFTEDBRANCH [31:0] $end
$var reg 32 ^ BRANCHADDRESS [31:0] $end
$upscope $end
$scope module branch_and $end
$var wire 1 ( DATA2 $end
$var wire 1 ' RESULT $end
$var wire 1 A DATA1 $end
$upscope $end
$scope module branch_select_mux $end
$var wire 32 _ DATA2 [31:0] $end
$var wire 1 ' SELECT $end
$var wire 32 ` DATA1 [31:0] $end
$var reg 32 a RESULT [31:0] $end
$upscope $end
$scope module control_unit $end
$var wire 8 b OPCODE [7:0] $end
$var reg 3 c ALU_OP [2:0] $end
$var reg 1 > ALU_SRC $end
$var reg 1 A BRANCH_SELECT $end
$var reg 1 : JUMP_SELECT $end
$var reg 1 * REG_WRITE $end
$var reg 1 , TWOS_COMP $end
$upscope $end
$scope module instruction_decoder $end
$var wire 32 d INSTRUCTION [31:0] $end
$var reg 8 e BRANCHADDRESS [7:0] $end
$var reg 8 f IMMIDIATE [7:0] $end
$var reg 8 g JUMPADDRESS [7:0] $end
$var reg 8 h OPCODE [7:0] $end
$var reg 3 i REGISTER_1 [2:0] $end
$var reg 3 j REGISTER_2 [2:0] $end
$var reg 3 k REGISTER_DEST [2:0] $end
$upscope $end
$scope module jump_concatenate $end
$var wire 32 l PCOUT [31:0] $end
$var wire 32 m LEFTSHIFTEDJUMP [31:0] $end
$var reg 32 n JUMPADDRESS [31:0] $end
$upscope $end
$scope module jump_select_mux $end
$var wire 32 o DATA1 [31:0] $end
$var wire 32 p DATA2 [31:0] $end
$var wire 1 : SELECT $end
$var reg 32 q RESULT [31:0] $end
$upscope $end
$scope module left_shift_for_branch $end
$var wire 32 r INPUT [31:0] $end
$var reg 32 s OUTPUT [31:0] $end
$upscope $end
$scope module left_shift_for_jump $end
$var wire 32 t INPUT [31:0] $end
$var reg 32 u OUTPUT [31:0] $end
$upscope $end
$scope module pc $end
$var wire 1 # CLK $end
$var wire 1 $ RESET $end
$var wire 32 v SELECTEDOUTPUT [31:0] $end
$var reg 32 w NEXTPCOUT [31:0] $end
$var reg 32 x PCOUT [31:0] $end
$upscope $end
$scope module reg_file $end
$var wire 1 # CLK $end
$var wire 8 y IN [7:0] $end
$var wire 3 z INADDRESS [2:0] $end
$var wire 8 { OUT1 [7:0] $end
$var wire 3 | OUT1ADDRESS [2:0] $end
$var wire 8 } OUT2 [7:0] $end
$var wire 3 ~ OUT2ADDRESS [2:0] $end
$var wire 1 $ RESET $end
$var wire 1 * WRITE $end
$upscope $end
$scope module sign_extender_for_branch $end
$var wire 8 !" INPUT [7:0] $end
$var reg 32 "" OUTPUT [31:0] $end
$upscope $end
$scope module sign_extender_for_jump $end
$var wire 8 #" INPUT [7:0] $end
$var reg 32 $" OUTPUT [31:0] $end
$upscope $end
$scope module twos_complement_mux $end
$var wire 8 %" DATA1 [7:0] $end
$var wire 1 , SELECT $end
$var wire 8 &" DATA2 [7:0] $end
$var reg 8 '" RESULT [7:0] $end
$upscope $end
$scope module twoscomp $end
$var wire 8 (" DATA [7:0] $end
$var reg 8 )" RESULT [7:0] $end
$upscope $end
$upscope $end
$upscope $end
$scope module cpu_tb $end
$scope module mycpu $end
$scope module reg_file $end
$var reg 8 *" \registers[0] [7:0] $end
$upscope $end
$upscope $end
$upscope $end
$scope module cpu_tb $end
$scope module mycpu $end
$scope module reg_file $end
$var reg 8 +" \registers[1] [7:0] $end
$upscope $end
$upscope $end
$upscope $end
$scope module cpu_tb $end
$scope module mycpu $end
$scope module reg_file $end
$var reg 8 ," \registers[2] [7:0] $end
$upscope $end
$upscope $end
$upscope $end
$scope module cpu_tb $end
$scope module mycpu $end
$scope module reg_file $end
$var reg 8 -" \registers[3] [7:0] $end
$upscope $end
$upscope $end
$upscope $end
$scope module cpu_tb $end
$scope module mycpu $end
$scope module reg_file $end
$var reg 8 ." \registers[4] [7:0] $end
$upscope $end
$upscope $end
$upscope $end
$scope module cpu_tb $end
$scope module mycpu $end
$scope module reg_file $end
$var reg 8 /" \registers[5] [7:0] $end
$upscope $end
$upscope $end
$upscope $end
$scope module cpu_tb $end
$scope module mycpu $end
$scope module reg_file $end
$var reg 8 0" \registers[6] [7:0] $end
$upscope $end
$upscope $end
$upscope $end
$scope module cpu_tb $end
$scope module mycpu $end
$scope module reg_file $end
$var reg 8 1" \registers[7] [7:0] $end
$upscope $end
$upscope $end
$upscope $end
$enddefinitions $end
$comment Show the parameter values. $end
$dumpall
$end
#0
$dumpvars
bx 1"
bx 0"
bx /"
bx ."
bx -"
bx ,"
bx +"
bx *"
bx )"
bx ("
bx '"
bx &"
bx %"
bx $"
bx #"
bx ""
bx !"
bx ~
bx }
bx |
bx {
bx z
bx y
bx x
bx w
bx v
bx u
bx t
bx s
bx r
bx q
bx p
bx o
bx n
bx m
bx l
bx k
bx j
bx i
bx h
bx g
bx f
bx e
bx d
bx c
bx b
bx a
bx `
bx _
bx ^
bx ]
bx \
bx [
bx Z
bx Y
bx X
bx W
bx V
bx U
bx T
bx S
bx R
bx Q
bx P
bx O
bx N
bx M
bx L
bx K
bx J
bx I
bx H
bx G
bx F
bx E
bx D
bx C
bx B
xA
bx @
bx ?
x>
bx =
bx <
bx ;
x:
bx 9
bx 8
bx 7
bx 6
bx 5
bx 4
bx 3
bx 2
bx 1
bx 0
bx /
bx .
bx -
x,
bx +
x*
bx )
x(
x'
bx &
b1000 %
1$
0#
bx "
bx !
$end
#4
1#
#5
b10000 7
b10000 m
b10000 u
b10000 8
b10000 ]
b10000 s
b100 .
b100 t
b100 $"
b100 /
b100 r
b100 ""
b100 ;
b100 g
b100 #"
b100 B
b100 e
b100 !"
b1010 ?
b1010 Y
b1010 f
b100 )
b100 k
b100 z
b10 2
b10 j
b10 ~
b0 3
b0 i
b0 |
b0 5
b0 b
b0 h
b1000000000000001010 "
b1000000000000001010 &
b1000000000000001010 d
b0 !
b0 4
b0 x
b0 1"
b0 0"
b0 /"
b0 ."
b0 -"
b0 ,"
b0 +"
b0 *"
#6
b100 9
b100 q
b100 v
b10100 C
b10100 ^
b10100 _
b100 @
b100 a
b100 o
b10100 <
b10100 n
b10100 p
b100 6
b100 \
b100 `
b100 l
b100 w
bx1x1x G
bx1x1x V
b0x0x0 K
b0x0x0 Q
0'
b1010 H
b1010 T
b1010 =
b1010 I
b1010 N
b1010 R
b1010 U
b1010 W
b1010 [
0:
0A
1*
1>
0,
b0 E
b0 F
b0 c
0$
#7
0(
b0 +
b0 Z
b0 '"
b1010 G
b1010 V
b0 K
b0 Q
b1010 L
b1010 P
b1010 D
b1010 M
b1010 y
b0 0
b0 }
b0 %"
b0 ("
b0 1
b0 J
b0 O
b0 S
b0 X
b0 {
#8
b0 -
b0 &"
b0 )"
0#
#12
1#
#13
b11000 <
b11000 n
b11000 p
b11000 C
b11000 ^
b11000 _
b10100 7
b10100 m
b10100 u
b10100 8
b10100 ]
b10100 s
b1 G
b1 V
b1 L
b1 P
b101 .
b101 t
b101 $"
b101 /
b101 r
b101 ""
b1 H
b1 T
b1 =
b1 I
b1 N
b1 R
b1 U
b1 W
b1 [
b101 ;
b101 g
b101 #"
b101 B
b101 e
b101 !"
b1 ?
b1 Y
b1 f
b101 )
b101 k
b101 z
b1 2
b1 j
b1 ~
b1010 ."
b1010000000000000001 "
b1010000000000000001 &
b1010000000000000001 d
b100 !
b100 4
b100 x
#14
b1000 9
b1000 q
b1000 v
b11100 C
b11100 ^
b11100 _
b1000 @
b1000 a
b1000 o
b11100 <
b11100 n
b11100 p
b1000 6
b1000 \
b1000 `
b1000 l
b1000 w
b1 D
b1 M
b1 y
#16
0#
#20
1#
#21
b100000 <
b100000 n
b100000 p
b100000 C
b100000 ^
b100000 _
b11000 7
b11000 m
b11000 u
b11000 8
b11000 ]
b11000 s
b110 .
b110 t
b110 $"
b110 /
b110 r
b110 ""
b110 ;
b110 g
b110 #"
b110 B
b110 e
b110 !"
b110 )
b110 k
b110 z
b1100000000000000001 "
b1100000000000000001 &
b1100000000000000001 d
b1000 !
b1000 4
b1000 x
b1 /"
#22
b1100 9
b1100 q
b1100 v
b100100 C
b100100 ^
b100100 _
b1100 @
b1100 a
b1100 o
b100100 <
b100100 n
b100100 p
b1100 6
b1100 \
b1100 `
b1100 l
b1100 w
#24
0#
#28
1#
