Lab06/CPU Programming Tools-20240416/alu.v
`define REG_SIZE 8
`define REG_ADDRESS_SIZE 3


module mov_module (DATA2,RESULT);
    input [`REG_SIZE-1:0] DATA2;
    output [`REG_SIZE-1:0] RESULT;

    assign RESULT = DATA2;

endmodule

module add_module (DATA1,DATA2,RESULT);
    input [`REG_SIZE-1:0] DATA1;
    input [`REG_SIZE-1:0] DATA2;
    output reg [`REG_SIZE-1:0] RESULT;
    
    always @(*) 
    begin   // add - sub
    if (DATA2 < 0)  // or we can use (DATA2[7]) as the condition
        RESULT = DATA1 - DATA2;
    else
        RESULT = DATA1 + DATA2;
    end

endmodule

module and_module (DATA1,DATA2,RESULT);
    input [`REG_SIZE-1:0] DATA1;
    input [`REG_SIZE-1:0] DATA2;
    output [`REG_SIZE-1:0] RESULT;

    assign RESULT = DATA1 & DATA2;

endmodule

module or_module (DATA1,DATA2,RESULT);
    input [`REG_SIZE-1:0] DATA1;
    input [`REG_SIZE-1:0] DATA2;
    output [`REG_SIZE-1:0] RESULT;

    assign RESULT = DATA1 | DATA2;


endmodule

module alu (DATA1,DATA2,RESULT,SELECT,ZERO);
    input [`REG_SIZE-1:0] DATA1;
    input [`REG_SIZE-1:0] DATA2;
    output reg [`REG_SIZE-1:0] RESULT; // if we want to use wire insted of reg , we woud have to use 'assign' to do that use internal_RESULT and assign to RESULT at the end
    input [`REG_ADDRESS_SIZE-1:0] SELECT;
    output reg ZERO;

    // making wires to have each module's answer.
    wire [`REG_SIZE-1:0] MOV_RESULT;     
    wire [`REG_SIZE-1:0] ADD_RESULT;
    wire [`REG_SIZE-1:0] AND_RESULT;
    wire [`REG_SIZE-1:0] OR_RESULT;

    // making instences for each module with seperated output 
    mov_module mov1(DATA2, MOV_RESULT);
    add_module add1(DATA1, DATA2, ADD_RESULT);
    and_module and1(DATA1, DATA2, AND_RESULT);
    or_module or1(DATA1, DATA2, OR_RESULT);

    // to check of result is zero for the branch if equal command
    always @(RESULT) begin
        if (RESULT == 0) begin
            ZERO = 1;
        end
        else begin
            ZERO = 0;
        end
    end

    // always block * to run the block whenever any input changes  
    always @(*)
    begin
        case (SELECT) //to SELECT what to output as a mux
        3'b000: // forward
            #1 RESULT = MOV_RESULT; 
        3'b001: // add or sub
            #2 RESULT = ADD_RESULT;
        3'b010: // and
            #1 RESULT = AND_RESULT;
        3'b011: // or
            #1 RESULT = OR_RESULT;
        //default: 3'b1xx is reserved        
        
        endcase
    end 
endmodule

Lab06/CPU Programming Tools-20240416/cpu.v
`include "alu.v"
`include "reg_file.v"

// Variables defined if have to change later(No effect when synthesising since all replace by it's value)
`define REG_ADDRESS_SIZE 3
`define REG_SIZE 8
`define OPCODE_SIZE 8
`define SH_AMT_SIZE 5
`define FUNC_SIZE 6
`define IMMIDIATE_SIZE 8
`define ADDRESS_SIZE 26
`define JUMP_SIZE 8


`define OPCODE_END 24
`define REGISTER_1_END 8
`define REGISTER_2_END 0
`define REGISTER_DEST_END 16

`define SH_AMT_END 6
`define FUNC_END 0
`define IMMIDIATE_END 0
`define ADDRESS_END 0
`define JUMP_END 16

`define ALU_OP_SIZE 3



// Module for size 8 mux
module mux_module8(DATA1,DATA2,RESULT,SELECT);
    input [`REG_SIZE-1:0] DATA1;
    input [`REG_SIZE-1:0] DATA2;
    output reg [`REG_SIZE-1:0] RESULT; // if we want to use wire insted of reg , we woud have to use 'assign' to do that use internal_RESULT and assign to RESULT at the end
    input SELECT;

    always @(*) begin // Selecting
        RESULT = SELECT ? DATA2 : DATA1;
    end

endmodule

// Module for size 32 mux
module mux_module32(DATA1,DATA2,RESULT,SELECT);
    input [31:0] DATA1;
    input [31:0] DATA2;
    output reg [31:0] RESULT; // if we want to use wire insted of reg , we woud have to use 'assign' to do that use internal_RESULT and assign to RESULT at the end
    input SELECT;

    always @(*) begin // Selecting
        RESULT = SELECT ? DATA2 : DATA1;
    end

endmodule

// Module for Two's complement
module twos_complement(DATA,RESULT);
    input [`REG_SIZE-1:0] DATA;
    output reg [`REG_SIZE-1:0] RESULT;

    always @(DATA) begin
        #1 RESULT = ~DATA + 1'b1; // Convering to the two's complement
    end

endmodule

// Programme counter module
module programme_counter(RESULT,NEXTRESULT,RESET,CLK);
    output reg [31:0] RESULT; 
    output reg [31:0] NEXTRESULT; 
    input RESET;
    input CLK;

    always @(posedge CLK) begin
        if (RESET) begin // Sets to zero of resset is  high
            RESULT <= #1 32'd0;
            NEXTRESULT <= #2 32'd4;
        end

        else begin // incrementing
            RESULT <= #1 NEXTRESULT;
            NEXTRESULT <= #2 NEXTRESULT + 32'd4;
        end
    end
    
endmodule


// Module for decoding instructions
module instruction_decoder(INSTRUCTION,OPCODE,REGISTER_1,REGISTER_2,REGISTER_DEST,IMMIDIATE,JUMPADDRESS);
    input [31:0] INSTRUCTION;
    output reg [`OPCODE_SIZE-1:0] OPCODE;
    output reg [`REG_ADDRESS_SIZE-1:0] REGISTER_1,REGISTER_2,REGISTER_DEST;
    output reg [`IMMIDIATE_SIZE-1:0] IMMIDIATE;
    output reg [`JUMP_SIZE-1:0] JUMPADDRESS;

    always @(INSTRUCTION) begin
        OPCODE = INSTRUCTION[`OPCODE_END + `OPCODE_SIZE : `OPCODE_END]; 
        REGISTER_1 = INSTRUCTION[`REGISTER_1_END + `REG_SIZE : `REGISTER_1_END];
        REGISTER_2 = INSTRUCTION[`REGISTER_2_END + `REG_SIZE : `REGISTER_2_END];
        REGISTER_DEST = INSTRUCTION[`REGISTER_DEST_END + `REG_SIZE : `REGISTER_DEST_END];
        IMMIDIATE = INSTRUCTION[`IMMIDIATE_END + `IMMIDIATE_SIZE : `IMMIDIATE_END];
        JUMPADDRESS = INSTRUCTION[`JUMP_END + `JUMP_SIZE : `JUMP_END];
    end

endmodule

// sign_extender
module sign_extender(INPUT,OUTPUT);
    input [`JUMP_SIZE-1:0] INPUT;
    output reg [31:0] OUTPUT;

    always @(INPUT) begin
        OUTPUT [31:`JUMP_SIZE] = 24'b0000_0000_0000_0000_0000_0000;
        OUTPUT [`JUMP_SIZE-1:0] = INPUT;
    end

endmodule

// left shift module
module left_shift(INPUT,OUTPUT);
    input [31:0] INPUT;
    output reg [31:0] OUTPUT;

    always @(INPUT) begin
        OUTPUT[31:2] = INPUT[29:0];
        OUTPUT[2:0] = 2'b00;
    end

endmodule

// jump_concatenate
module jump_concatenate(PCOUT,LEFTSHIFTEDJUMP,JUMPADDRESS);
    input [31:0] PCOUT;
    input [31:0] LEFTSHIFTEDJUMP;
    output reg [31:0] JUMPADDRESS;

    always @(PCOUT,LEFTSHIFTEDJUMP) begin
        JUMPADDRESS[31:28] = PCOUT[31:28];
        JUMPADDRESS[27:0] = LEFTSHIFTEDJUMP[27:0];
    end

endmodule

// and module for branch if equal instruction
module branch_and(DATA1,DATA2,RESULT);
    input DATA1;
    input DATA2;
    output RESULT;

    assign RESULT = DATA1 & DATA2;

endmodule

// add module for branch if equal instruction
module branch_add(PCOUT,LEFTSHIFTEDBRANCH,BRANCHADDRESS);
    input [31:0] PCOUT;
    input [31:0] LEFTSHIFTEDBRANCH;
    output reg [31:0] BRANCHADDRESS;

    always @(PCOUT,LEFTSHIFTEDBRANCH) begin
        BRANCHADDRESS = PCOUT + LEFTSHIFTEDBRANCH;
    end    
endmodule

// add, sub, and, or, mov, loadi
module control_unit(OPCODE,ALU_OP,ALU_SRC,REG_WRITE,TWOS_COMP,BRANCH_SELECT,JUMP_SELECT);
    input [`OPCODE_SIZE-1:0] OPCODE;
    output reg ALU_SRC,REG_WRITE,TWOS_COMP,BRANCH_SELECT,JUMP_SELECT;
    output reg [`ALU_OP_SIZE-1:0] ALU_OP;

    // always block * to run the block whenever any input changes  
    always @(*)
    begin
        #1 // Decorder delay
        case (OPCODE) 
        8'b00000000: // loadi
        begin
            ALU_OP = 3'b000; //ALUOP COMMAND
            TWOS_COMP = 1'b0;
            ALU_SRC = 1'b1;
            REG_WRITE = 1'b1;
            BRANCH_SELECT = 1'b0;
            JUMP_SELECT = 1'b0;
        end
        8'b00000001: // mov
        begin
            ALU_OP = 3'b000; //ALUOP COMMAND
            TWOS_COMP = 1'b0;
            ALU_SRC = 1'b0;
            REG_WRITE = 1'b1;
            BRANCH_SELECT = 1'b0;
            JUMP_SELECT = 1'b0;     
        end   
        8'b00000010: // add
        begin
            ALU_OP = 3'b001; //ALUOP COMMAND
            TWOS_COMP = 1'b0;
            ALU_SRC = 1'b0;
            REG_WRITE = 1'b1;
            BRANCH_SELECT = 1'b0;
            JUMP_SELECT = 1'b0;   
        end
        8'b00000011: // sub
        begin
            ALU_OP = 3'b001; //ALUOP COMMAND
            TWOS_COMP = 1'b1;
            ALU_SRC = 1'b0;
            REG_WRITE = 1'b1;
            BRANCH_SELECT = 1'b0;
            JUMP_SELECT = 1'b0;  
        end
        8'b00000100: // and
        begin
            ALU_OP = 3'b010; //ALUOP COMMAND
            TWOS_COMP = 1'b0;
            ALU_SRC = 1'b0;
            REG_WRITE = 1'b1;
            BRANCH_SELECT = 1'b0;
            JUMP_SELECT = 1'b0; 
        end  
        8'b00000101: // or
        begin
            ALU_OP = 3'b011; //ALUOP COMMAND
            TWOS_COMP = 1'b0;
            ALU_SRC = 1'b0;
            REG_WRITE = 1'b1; 
            BRANCH_SELECT = 1'b0;
            JUMP_SELECT = 1'b0;  
        end   
        8'b00000110: // j 
        begin
            ALU_OP = 3'b000; //ALUOP COMMAND
            TWOS_COMP = 1'b0;
            ALU_SRC = 1'b0;
            REG_WRITE = 1'b0; 
            BRANCH_SELECT = 1'b0;
            JUMP_SELECT = 1'b1;  
        end  
        8'b00000111: // beq
        begin
            ALU_OP = 3'b000; //ALUOP COMMAND
            TWOS_COMP = 1'b0;
            ALU_SRC = 1'b0;
            REG_WRITE = 1'b0; 
            BRANCH_SELECT = 1'b1;
            JUMP_SELECT = 1'b0;  
        end 
        endcase
    end 

endmodule

	// char *op_j		= "00000110";
	// char *op_beq	= "00000111";

module cpu(PCOUT, INSTRUCTION, CLK, RESET);
    input wire [31:0] INSTRUCTION;
    input wire CLK;
    input wire RESET;

    //programe counter
    output wire [31:0] PCOUT;
    output wire [31:0] NEXTPCOUT;

    //instruction_decoder
    wire [`IMMIDIATE_SIZE-1:0] IMMIDIATE;
    wire [`REG_ADDRESS_SIZE-1:0] READREG2;
    wire [`REG_ADDRESS_SIZE-1:0] READREG1;
    wire [`REG_ADDRESS_SIZE-1:0] WRITEREG;
    wire [`OPCODE_SIZE-1:0] OPCODE;
    wire [`JUMP_SIZE-1:0] JUMPINSTRUCTION;

    //sign_extender
    wire [31:0] SIGNEXTENDEDJUMP;
    wire [31:0] SIGNEXTENDEDBRANCH;

    //left_shift
    wire [31:0] LEFTSHIFTEDJUMP;
    wire [31:0] LEFTSHIFTEDBRANCH;

    //jump_concatenator
    wire [31:0] JUMPADDRESS;

    //branch_add
    wire [31:0] BRANCHADDRESS;

    //branch_and
    wire ZERO_and_BRANCHSELECT;

    //control_unit
    wire WRITEENABLE;
    wire TWOS_COMP_SELECT;
    wire IMMIDIATE_SELECT;
    wire [`ALU_OP_SIZE-1:0] ALUOP;
    wire BRANCH_SELECT;
    wire JUMP_SELECT;

    //register_file
    wire [`REG_SIZE-1:0] REGOUT2;
    wire [`REG_SIZE-1:0] REGOUT1;

    //twos_compliment
    wire [`REG_SIZE-1:0] TWOS_COMP;

    //mux
    wire [`REG_SIZE-1:0] TWOS_COMP_SELECTED;
    wire [`REG_SIZE-1:0] IMMIDIATE_SELECTED;
    wire [31:0] BRANCH_SELECTED;
    wire [31:0] JUMP_SELECTED;

    //alu
    wire [`REG_SIZE-1:0] ALURESULT;
    wire ZERO;

    programme_counter pc(PCOUT,NEXTPCOUT,RESET,CLK); // The programme counter
    instruction_decoder instruction_decoder(INSTRUCTION,OPCODE,READREG1,READREG2,WRITEREG,IMMIDIATE,JUMPINSTRUCTION);   // The instruction decorder
    
    sign_extender sign_extender_for_jump(JUMPINSTRUCTION,SIGNEXTENDEDJUMP);     // sign extend for jump instruction
    left_shift left_shift_for_jump(SIGNEXTENDEDJUMP,LEFTSHIFTEDJUMP);   // left shift for jump instruction 
    jump_concatenate jump_concatenate(NEXTPCOUT,LEFTSHIFTEDJUMP,JUMPADDRESS);   // jump concatenator

    sign_extender sign_extender_for_branch(IMMIDIATE,SIGNEXTENDEDBRANCH);   // sign extended for branch imidiate value
    left_shift left_shift_for_branch(SIGNEXTENDEDBRANCH,LEFTSHIFTEDBRANCH); // left shift for branch iimidiate value
    branch_add branch_add(NEXTPCOUT,LEFTSHIFTEDBRANCH,BRANCHADDRESS);    // adding address to PC+4 for branch instruction

    control_unit control_unit(OPCODE,ALUOP,IMMIDIATE_SELECT,WRITEENABLE,TWOS_COMP_SELECT,BRANCH_SELECT,JUMP_SELECT);  // Control unit

    reg_file reg_file(ALURESULT,REGOUT1,REGOUT2,WRITEREG,READREG1,READREG2,WRITEENABLE,CLK,RESET);  // Register file
    twos_complement twoscomp(REGOUT2,TWOS_COMP);    // Twos complement 

    mux_module8 twos_complement_mux(REGOUT2,TWOS_COMP,TWOS_COMP_SELECTED,TWOS_COMP_SELECT);      // mux to select the two's complement
    mux_module8 alu_immidiate_mux(TWOS_COMP_SELECTED,IMMIDIATE,IMMIDIATE_SELECTED,IMMIDIATE_SELECT);     // Mux to select the immidate value from the instruction
    
    branch_and branch_and(BRANCH_SELECT,ZERO,ZERO_and_BRANCHSELECT);    // and gate for if_Zero and Branch control signal
    mux_module32 branch_select_mux(PCOUT,BRANCHADDRESS,BRANCH_SELECTED,ZERO_and_BRANCHSELECT); // selcting mux whether to branch or not

    mux_module32 jump_select_mux(BRANCH_SELECTED,JUMPADDRESS,JUMP_SELECTED,JUMP_SELECT); // selcting mux whether to branch or not

    alu alu(REGOUT1,IMMIDIATE_SELECTED,ALURESULT,ALUOP,ZERO);    // The ALU 

endmodule

Lab06/CPU Programming Tools-20240416/group19_lab6_part1/reg_file.v
`define REG_ADDRESS_SIZE 3 // Size of a register address
`define REG_SIZE 8 // size of a register

module reg_file(IN,OUT1,OUT2,INADDRESS,OUT1ADDRESS,OUT2ADDRESS, WRITE, CLK, RESET);
    input [`REG_SIZE-1:0] IN;
    input [`REG_ADDRESS_SIZE-1:0] OUT1ADDRESS, OUT2ADDRESS, INADDRESS;
    output [`REG_SIZE-1:0] OUT1, OUT2;
    input WRITE, CLK, RESET;

    // Internal register array
    reg [`REG_SIZE-1:0] registers[`REG_SIZE-1:0];

    // Assign outputs to internal latches
    assign #2 OUT1 = registers[OUT1ADDRESS];         
    assign #2 OUT2 = registers[OUT2ADDRESS];
    
    always @(posedge CLK)
    begin

        if (RESET) // If reset is high
        begin
            // Reset all registers to 0 with time delay of #1
            registers[0] <= #1 8'b0;
            registers[1] <= #1 8'b0;
            registers[2] <= #1 8'b0;
            registers[3] <= #1 8'b0;
            registers[4] <= #1 8'b0;
            registers[5] <= #1 8'b0;
            registers[6] <= #1 8'b0;
            registers[7] <= #1 8'b0;
        end
        
        else if (WRITE) // If write is high
        begin
            registers[INADDRESS] <= #1 IN; // #1 propergation delay
        end

    end

endmodule

Lab06/CPU Programming Tools-20240416/cpu_tb.v
// Computer Architecture (CO224) - Lab 05
// Design: Testbench of Integrated CPU of Simple Processor
// Author: Isuru Nawinne

`include "cpu.v"

module cpu_tb;

    reg CLK, RESET;
    wire [31:0] PC;
    wire [31:0] INSTRUCTION;

    
    // TODO: Initialize an array of registers (8x1024) named 'instr_mem' to be used as instruction memory
    reg [7:0] instr_mem [1023:0];
    
    // TODO: Create combinational logic to support CPU instruction fetching, given the Program Counter(PC) value 
    //       (make sure you include the delay for instruction fetching here)
    assign INSTRUCTION = {instr_mem[PC+3], instr_mem[PC+2], instr_mem[PC+1], instr_mem[PC]};
    
    initial
    begin
        // Initialize instruction memory with the set of instructions you need execute on CPU
        
        // METHOD 1: manually loading instructions to instr_mem
        // {instr_mem[10'd3], instr_mem[10'd2], instr_mem[10'd1], instr_mem[10'd0]} = 32'b00000000000001000000000000000101;
        // {instr_mem[10'd7], instr_mem[10'd6], instr_mem[10'd5], instr_mem[10'd4]} = 32'b00000000000000100000000000001001;
        // {instr_mem[10'd11], instr_mem[10'd10], instr_mem[10'd9], instr_mem[10'd8]} = 32'b00000010000001100000010000000010;
        
        // METHOD 2: loading instr_mem content from instr_mem.mem file
        $readmemb("instr_mem.mem", instr_mem,0,1023);
    end
    
    /* 
    -----
     CPU
    -----
    */
    cpu mycpu(PC, INSTRUCTION, CLK, RESET);
    
    integer i;
    initial
    begin
    
        // generate files needed to plot the waveform using GTKWave
        $dumpfile("cpu_wavedata.vcd");
		$dumpvars(0, cpu_tb);
        
        for (i=0 ;i<8;i=i+1)
            $dumpvars(1,cpu_tb.mycpu.reg_file.registers[i]);
        
        CLK = 1'b0;
        RESET = 1'b0;
        
        // TODO: Reset the CPU (by giving a pulse to RESET signal) to start the program execution
        RESET = 1'b1;
        #6
        RESET = 1'b0;
        
        // finish simulation after some time
        #500
        $finish;
        
    end
    
    // clock signal generation
    always
        #4 CLK = ~CLK;
        

endmodule

Lab06/CPU Programming Tools-20240416/cpu_wavedata.vcd
$date
	Wed May 08 14:12:44 2024
$end
$version
	Icarus Verilog
$end
$timescale
	1s
$end
$scope module cpu_tb $end
$var wire 32 ! PC [31:0] $end
$var wire 32 " INSTRUCTION [31:0] $end
$var reg 1 # CLK $end
$var reg 1 $ RESET $end
$var integer 32 % i [31:0] $end
$scope module mycpu $end
$var wire 1 # CLK $end
$var wire 32 & INSTRUCTION [31:0] $end
$var wire 1 $ RESET $end
$var wire 1 ' ZERO_and_BRANCHSELECT $end
$var wire 1 ( ZERO $end
$var wire 3 ) WRITEREG [2:0] $end
$var wire 1 * WRITEENABLE $end
$var wire 8 + TWOS_COMP_SELECTED [7:0] $end
$var wire 1 , TWOS_COMP_SELECT $end
$var wire 8 - TWOS_COMP [7:0] $end
$var wire 32 . SIGNEXTENDEDJUMP [31:0] $end
$var wire 32 / SIGNEXTENDEDBRANCH [31:0] $end
$var wire 8 0 REGOUT2 [7:0] $end
$var wire 8 1 REGOUT1 [7:0] $end
$var wire 3 2 READREG2 [2:0] $end
$var wire 3 3 READREG1 [2:0] $end
$var wire 32 4 PCOUT [31:0] $end
$var wire 8 5 OPCODE [7:0] $end
$var wire 32 6 NEXTPCOUT [31:0] $end
$var wire 32 7 LEFTSHIFTEDJUMP [31:0] $end
$var wire 32 8 LEFTSHIFTEDBRANCH [31:0] $end
$var wire 32 9 JUMP_SELECTED [31:0] $end
$var wire 1 : JUMP_SELECT $end
$var wire 8 ; JUMPINSTRUCTION [7:0] $end
$var wire 32 < JUMPADDRESS [31:0] $end
$var wire 8 = IMMIDIATE_SELECTED [7:0] $end
$var wire 1 > IMMIDIATE_SELECT $end
$var wire 8 ? IMMIDIATE [7:0] $end
$var wire 32 @ BRANCH_SELECTED [31:0] $end
$var wire 1 A BRANCH_SELECT $end
$var wire 32 B BRANCHADDRESS [31:0] $end
$var wire 8 C ALURESULT [7:0] $end
$var wire 3 D ALUOP [2:0] $end
$scope module alu $end
$var wire 3 E SELECT [2:0] $end
$var wire 8 F OR_RESULT [7:0] $end
$var wire 8 G MOV_RESULT [7:0] $end
$var wire 8 H DATA2 [7:0] $end
$var wire 8 I DATA1 [7:0] $end
$var wire 8 J AND_RESULT [7:0] $end
$var wire 8 K ADD_RESULT [7:0] $end
$var reg 8 L RESULT [7:0] $end
$var reg 1 ( ZERO $end
$scope module add1 $end
$var wire 8 M DATA2 [7:0] $end
$var wire 8 N DATA1 [7:0] $end
$var reg 8 O RESULT [7:0] $end
$upscope $end
$scope module and1 $end
$var wire 8 P RESULT [7:0] $end
$var wire 8 Q DATA2 [7:0] $end
$var wire 8 R DATA1 [7:0] $end
$upscope $end
$scope module mov1 $end
$var wire 8 S RESULT [7:0] $end
$var wire 8 T DATA2 [7:0] $end
$upscope $end
$scope module or1 $end
$var wire 8 U RESULT [7:0] $end
$var wire 8 V DATA2 [7:0] $end
$var wire 8 W DATA1 [7:0] $end
$upscope $end
$upscope $end
$scope module alu_immidiate_mux $end
$var wire 1 > SELECT $end
$var wire 8 X DATA2 [7:0] $end
$var wire 8 Y DATA1 [7:0] $end
$var reg 8 Z RESULT [7:0] $end
$upscope $end
$scope module branch_add $end
$var wire 32 [ PCOUT [31:0] $end
$var wire 32 \ LEFTSHIFTEDBRANCH [31:0] $end
$var reg 32 ] BRANCHADDRESS [31:0] $end
$upscope $end
$scope module branch_and $end
$var wire 1 ( DATA2 $end
$var wire 1 ' RESULT $end
$var wire 1 A DATA1 $end
$upscope $end
$scope module branch_select_mux $end
$var wire 32 ^ DATA2 [31:0] $end
$var wire 1 ' SELECT $end
$var wire 32 _ DATA1 [31:0] $end
$var reg 32 ` RESULT [31:0] $end
$upscope $end
$scope module control_unit $end
$var wire 8 a OPCODE [7:0] $end
$var reg 3 b ALU_OP [2:0] $end
$var reg 1 > ALU_SRC $end
$var reg 1 A BRANCH_SELECT $end
$var reg 1 : JUMP_SELECT $end
$var reg 1 * REG_WRITE $end
$var reg 1 , TWOS_COMP $end
$upscope $end
$scope module instruction_decoder $end
$var wire 32 c INSTRUCTION [31:0] $end
$var reg 8 d IMMIDIATE [7:0] $end
$var reg 8 e JUMPADDRESS [7:0] $end
$var reg 8 f OPCODE [7:0] $end
$var reg 3 g REGISTER_1 [2:0] $end
$var reg 3 h REGISTER_2 [2:0] $end
$var reg 3 i REGISTER_DEST [2:0] $end
$upscope $end
$scope module jump_concatenate $end
$var wire 32 j PCOUT [31:0] $end
$var wire 32 k LEFTSHIFTEDJUMP [31:0] $end
$var reg 32 l JUMPADDRESS [31:0] $end
$upscope $end
$scope module jump_select_mux $end
$var wire 32 m DATA1 [31:0] $end
$var wire 32 n DATA2 [31:0] $end
$var wire 1 : SELECT $end
$var reg 32 o RESULT [31:0] $end
$upscope $end
$scope module left_shift_for_branch $end
$var wire 32 p INPUT [31:0] $end
$var reg 32 q OUTPUT [31:0] $end
$upscope $end
$scope module left_shift_for_jump $end
$var wire 32 r INPUT [31:0] $end
$var reg 32 s OUTPUT [31:0] $end
$upscope $end
$scope module pc $end
$var wire 1 # CLK $end
$var wire 1 $ RESET $end
$var reg 32 t NEXTRESULT [31:0] $end
$var reg 32 u RESULT [31:0] $end
$upscope $end
$scope module reg_file $end
$var wire 1 # CLK $end
$var wire 8 v IN [7:0] $end
$var wire 3 w INADDRESS [2:0] $end
$var wire 8 x OUT1 [7:0] $end
$var wire 3 y OUT1ADDRESS [2:0] $end
$var wire 8 z OUT2 [7:0] $end
$var wire 3 { OUT2ADDRESS [2:0] $end
$var wire 1 $ RESET $end
$var wire 1 * WRITE $end
$upscope $end
$scope module sign_extender_for_branch $end
$var wire 8 | INPUT [7:0] $end
$var reg 32 } OUTPUT [31:0] $end
$upscope $end
$scope module sign_extender_for_jump $end
$var wire 8 ~ INPUT [7:0] $end
$var reg 32 !" OUTPUT [31:0] $end
$upscope $end
$scope module twos_complement_mux $end
$var wire 8 "" DATA1 [7:0] $end
$var wire 1 , SELECT $end
$var wire 8 #" DATA2 [7:0] $end
$var reg 8 $" RESULT [7:0] $end
$upscope $end
$scope module twoscomp $end
$var wire 8 %" DATA [7:0] $end
$var reg 8 &" RESULT [7:0] $end
$upscope $end
$upscope $end
$upscope $end
$scope module cpu_tb $end
$scope module mycpu $end
$scope module reg_file $end
$var reg 8 '" \registers[0] [7:0] $end
$upscope $end
$upscope $end
$upscope $end
$scope module cpu_tb $end
$scope module mycpu $end
$scope module reg_file $end
$var reg 8 (" \registers[1] [7:0] $end
$upscope $end
$upscope $end
$upscope $end
$scope module cpu_tb $end
$scope module mycpu $end
$scope module reg_file $end
$var reg 8 )" \registers[2] [7:0] $end
$upscope $end
$upscope $end
$upscope $end
$scope module cpu_tb $end
$scope module mycpu $end
$scope module reg_file $end
$var reg 8 *" \registers[3] [7:0] $end
$upscope $end
$upscope $end
$upscope $end
$scope module cpu_tb $end
$scope module mycpu $end
$scope module reg_file $end
$var reg 8 +" \registers[4] [7:0] $end
$upscope $end
$upscope $end
$upscope $end
$scope module cpu_tb $end
$scope module mycpu $end
$scope module reg_file $end
$var reg 8 ," \registers[5] [7:0] $end
$upscope $end
$upscope $end
$upscope $end
$scope module cpu_tb $end
$scope module mycpu $end
$scope module reg_file $end
$var reg 8 -" \registers[6] [7:0] $end
$upscope $end
$upscope $end
$upscope $end
$scope module cpu_tb $end
$scope module mycpu $end
$scope module reg_file $end
$var reg 8 ." \registers[7] [7:0] $end
$upscope $end
$upscope $end
$upscope $end
$enddefinitions $end
$comment Show the parameter values. $end
$dumpall
$end
#0
$dumpvars
bx ."
bx -"
bx ,"
bx +"
bx *"
bx )"
bx ("
bx '"
bx &"
bx %"
bx $"
bx #"
bx ""
bx !"
bx ~
bx }
bx |
bx {
bx z
bx y
bx x
bx w
bx v
bx u
bx t
bx s
bx r
bx q
bx p
bx o
bx n
bx m
bx l
bx k
bx j
bx i
bx h
bx g
bx f
bx e
bx d
bx c
bx b
bx a
bx `
bx _
bx ^
bx ]
bx \
bx [
bx Z
bx Y
bx X
bx W
bx V
bx U
bx T
bx S
bx R
bx Q
bx P
bx O
bx N
bx M
bx L
bx K
bx J
bx I
bx H
bx G
bx F
bx E
bx D
bx C
bx B
xA
bx @
bx ?
x>
bx =
bx <
bx ;
x:
bx 9
bx 8
bx 7
bx 6
bx 5
bx 4
bx 3
bx 2
bx 1
bx 0
bx /
bx .
bx -
x,
bx +
x*
bx )
x(
x'
bx &
b1000 %
1$
0#
bx "
bx !
$end
#4
1#
#5
bx0000000000000000000000010000 <
bx0000000000000000000000010000 l
bx0000000000000000000000010000 n
b10000 7
b10000 k
b10000 s
b10000 8
b10000 \
b10000 q
b100 .
b100 r
b100 !"
b101 /
b101 p
b101 }
b100 ;
b100 e
b100 ~
b101 ?
b101 X
b101 d
b101 |
b100 )
b100 i
b100 w
b101 2
b101 h
b101 {
b0 3
b0 g
b0 y
b0 5
b0 a
b0 f
b1000000000000000101 "
b1000000000000000101 &
b1000000000000000101 c
b0 !
b0 4
b0 _
b0 u
b0 ."
b0 -"
b0 ,"
b0 +"
b0 *"
b0 )"
b0 ("
b0 '"
#6
b10100 B
b10100 ]
b10100 ^
b10000 <
b10000 l
b10000 n
b100 6
b100 [
b100 j
b100 t
b0 9
b0 o
b0 @
b0 `
b0 m
bx1x1 F
bx1x1 U
b0x0x J
b0x0x P
0'
b101 G
b101 S
b101 =
b101 H
b101 M
b101 Q
b101 T
b101 V
b101 Z
0:
0A
1*
1>
0,
b0 D
b0 E
b0 b
0$
#7
0(
b0 +
b0 Y
b0 $"
b101 F
b101 U
b0 J
b0 P
b101 K
b101 O
b101 C
b101 L
b101 v
b0 0
b0 z
b0 ""
b0 %"
b0 1
b0 I
b0 N
b0 R
b0 W
b0 x
#8
b0 -
b0 #"
b0 &"
0#
#12
1#
#13
b1000 <
b1000 l
b1000 n
b100100 B
b100100 ]
b100100 ^
b1000 7
b1000 k
b1000 s
b1001 F
b1001 U
b1001 K
b1001 O
b100000 8
b100000 \
b100000 q
b10 .
b10 r
b10 !"
b1001 G
b1001 S
b1001 =
b1001 H
b1001 M
b1001 Q
b1001 T
b1001 V
b1001 Z
b1001 /
b1001 p
b1001 }
b100 9
b100 o
b10 ;
b10 e
b10 ~
b1001 ?
b1001 X
b1001 d
b1001 |
b10 )
b10 i
b10 w
b1 2
b1 h
b1 {
b100 @
b100 `
b100 m
b101 +"
b100000000000001001 "
b100000000000001001 &
b100000000000001001 c
b100 !
b100 4
b100 _
b100 u
#14
b101000 B
b101000 ]
b101000 ^
b1000 6
b1000 [
b1000 j
b1000 t
b1001 C
b1001 L
b1001 v
#16
0#
#20
1#
#21
b11000 <
b11000 l
b11000 n
b10000 B
b10000 ]
b10000 ^
b11000 7
b11000 k
b11000 s
b10 F
b10 U
b10 K
b10 O
b1000 8
b1000 \
b1000 q
b110 .
b110 r
b110 !"
b10 G
b10 S
b10 =
b10 H
b10 M
b10 Q
b10 T
b10 V
b10 Z
b10 /
b10 p
b10 }
b1000 9
b1000 o
b110 ;
b110 e
b110 ~
b10 ?
b10 X
b10 d
b10 |
b110 )
b110 i
b110 w
b10 2
b10 h
b10 {
b100 3
b100 g
b100 y
b10 5
b10 a
b10 f
b1000 @
b1000 `
b1000 m
b10000001100000010000000010 "
b10000001100000010000000010 &
b10000001100000010000000010 c
b1000 !
b1000 4
b1000 _
b1000 u
b1001 )"
#22
b10100 B
b10100 ]
b10100 ^
b1100 6
b1100 [
b1100 j
b1100 t
b0 F
b0 U
b0 K
b0 O
b0 G
b0 S
b0 =
b0 H
b0 M
b0 Q
b0 T
b0 V
b0 Z
b10 C
b10 L
b10 v
0>
b1 D
b1 E
b1 b
#23
b1 J
b1 P
b1001 G
b1001 S
b1001 =
b1001 H
b1001 M
b1001 Q
b1001 T
b1001 V
b1001 Z
b1001 +
b1001 Y
b1001 $"
b1101 F
b1101 U
b1110 K
b1110 O
b1001 0
b1001 z
b1001 ""
b1001 %"
b101 1
b101 I
b101 N
b101 R
b101 W
b101 x
#24
b11110111 -
b11110111 #"
b11110111 &"
b1110 C
b1110 L
b1110 v
0#
#28
1#
