Lab06/CPU Programming Tools-20240416/reg_file.v
`define REG_ADDRESS_SIZE 3
`define REG_SIZE 8

module reg_file(IN,OUT1,OUT2,INADDRESS,OUT1ADDRESS,OUT2ADDRESS, WRITE, CLK, RESET);
    input [`REG_SIZE-1:0] IN;
    input [`REG_ADDRESS_SIZE-1:0] OUT1ADDRESS, OUT2ADDRESS, INADDRESS;
    output [`REG_SIZE-1:0] OUT1, OUT2;
    input WRITE, CLK, RESET;

    // Internal register array
    reg [`REG_SIZE-1:0] registers[`REG_SIZE-1:0];

    // Output register (registers required since we cant assign if not registers)
    reg [`REG_SIZE-1:0] out1_reg;
    reg [`REG_SIZE-1:0] out2_reg;

    // Assign outputs to internal latches
    assign OUT1 = out1_reg;         
    assign OUT2 = out2_reg;
    
    always @(posedge CLK)
    begin
        if (RESET) // If reset is high
        begin
            // Reset all registers to 0 with time delay of #1
            registers[0] <= #1 8'b0;
            registers[1] <= #1 8'b0;
            registers[2] <= #1 8'b0;
            registers[3] <= #1 8'b0;
            registers[4] <= #1 8'b0;
            registers[5] <= #1 8'b0;
            registers[6] <= #1 8'b0;
            registers[7] <= #1 8'b0;
        end
        
        else if (WRITE) // If write is high
        begin
            registers[INADDRESS] <= #1 IN; // #1 propergation delay
        end
        
        else  // Else times output should be what ever address the pointers are pointing at
        begin   // Outputting values with #2 delay 
            out1_reg <= #2 registers[OUT1ADDRESS];      //here registers are reqired , since wirescant be used to store values
            out2_reg <= #2 registers[OUT2ADDRESS];
        end

    end

endmodule

Lab06/CPU Programming Tools-20240416/alu.v
`define REG_SIZE 8
`define REG_ADDRESS_SIZE 3


module mov_module (DATA2,RESULT);
    input [`REG_SIZE-1:0] DATA2;
    output [`REG_SIZE-1:0] RESULT;

    assign RESULT = DATA2;

endmodule

module add_module (DATA1,DATA2,RESULT);
    input [`REG_SIZE-1:0] DATA1;
    input [`REG_SIZE-1:0] DATA2;
    output reg [`REG_SIZE-1:0] RESULT;
    
    always @(*) 
    begin   // add - sub
    if (DATA2 < 0)  // or we can use (DATA2[7]) as the condition
        RESULT = DATA1 - DATA2;
    else
        RESULT = DATA1 + DATA2;
    end

endmodule

module and_module (DATA1,DATA2,RESULT);
    input [`REG_SIZE-1:0] DATA1;
    input [`REG_SIZE-1:0] DATA2;
    output [`REG_SIZE-1:0] RESULT;

    assign RESULT = DATA1 & DATA2;

endmodule

module or_module (DATA1,DATA2,RESULT);
    input [`REG_SIZE-1:0] DATA1;
    input [`REG_SIZE-1:0] DATA2;
    output [`REG_SIZE-1:0] RESULT;

    assign RESULT = DATA1 | DATA2;

endmodule

module mult_module (DATA1,DATA2,RESULT);
    input [`REG_SIZE-1:0] DATA1;
    input [`REG_SIZE-1:0] DATA2;
    output [`REG_SIZE-1:0] RESULT;

    assign RESULT = DATA1 * DATA2;

endmodule

module logical_shift (DATA, SHIFTAMOUNT, RESULT);
    input [`REG_SIZE-1:0] DATA;
    input [`REG_SIZE-1:0] SHIFTAMOUNT;
    reg [`REG_SIZE-1:0] OFFSET;
    output reg [`REG_SIZE-1:0] RESULT;

    integer i;
    integer j;
    always @(*) begin
        RESULT = DATA;
        OFFSET = SHIFTAMOUNT;
        if (!SHIFTAMOUNT[`REG_SIZE-1]) begin // left shift
            for (i = 0; i < OFFSET; i = i + 1) begin
                for (j = 0; j < `REG_SIZE; j = j + 1) begin
                    RESULT[j] = RESULT[j - 1];
                    if (j == 0) begin
                    RESULT[j] = 1'b0;   
                    end
                end
            end
        end
        else if (SHIFTAMOUNT[`REG_SIZE-1]) begin // right shift
            OFFSET = -SHIFTAMOUNT;
            for (i = 0; i < OFFSET; i = i + 1) begin
                for (j = 0; j < `REG_SIZE; j = j + 1) begin
                    RESULT[j] = RESULT[j + 1];
                    if (j == `REG_SIZE-1) begin
                    RESULT[j] = 1'b0;   
                    end
                end          
            end
        end
    end
endmodule

module arithmatic_shift (DATA, SHIFTAMOUNT, RESULT);
    input [`REG_SIZE-1:0] DATA;
    input [`REG_SIZE-1:0] SHIFTAMOUNT;
    reg [`REG_SIZE-1:0] OFFSET;
    output reg [`REG_SIZE-1:0] RESULT;
    integer i;
    always @(*) begin
        RESULT = DATA;
            OFFSET = SHIFTAMOUNT;
        if (!SHIFTAMOUNT[`REG_SIZE-1]) begin // left shift
            for (i = 0; i < OFFSET; i = i + 1) begin
                RESULT = RESULT * 2;
            end
        end
        else if (SHIFTAMOUNT[`REG_SIZE-1]) begin // right shift
            OFFSET = -SHIFTAMOUNT;
            for (i = 0; i < OFFSET; i = i + 1) begin
                RESULT = RESULT / 2;
            end
        end
    end


endmodule


module alu (DATA1,DATA2,RESULT,SELECT,ZERO);
    input [`REG_SIZE-1:0] DATA1;
    input [`REG_SIZE-1:0] DATA2;
    output reg [`REG_SIZE-1:0] RESULT; // if we want to use wire insted of reg , we woud have to use 'assign' to do that use internal_RESULT and assign to RESULT at the end
    input [`REG_ADDRESS_SIZE-1:0] SELECT;
    output reg ZERO;

    // making wires to have each module's answer.
    wire [`REG_SIZE-1:0] MOV_RESULT;     
    wire [`REG_SIZE-1:0] ADD_RESULT;
    wire [`REG_SIZE-1:0] AND_RESULT;
    wire [`REG_SIZE-1:0] OR_RESULT;
    wire [`REG_SIZE-1:0] MULT_RESULT;
    wire [`REG_SIZE-1:0] SL_RESULT; // shift locically (left or right)


    // making instences for each module with seperated output 
    mov_module mov1(DATA2, MOV_RESULT);
    add_module add1(DATA1, DATA2, ADD_RESULT);
    and_module and1(DATA1, DATA2, AND_RESULT);
    or_module or1(DATA1, DATA2, OR_RESULT);
    mult_module mult1(DATA1, DATA2, MULT_RESULT);
    logical_shift sl1(DATA1, DATA2, SL_RESULT);


    // to check of result is zero for the branch if equal command
    always @(*) begin
        if (!ADD_RESULT) begin
            ZERO = 1;
        end
        else begin
            ZERO = 0;
        end
    end

    // always block * to run the block whenever any input changes  
    always @(*)
    begin
        case (SELECT) //to SELECT what to output as a mux
        3'b000: // forward
            #1 RESULT = MOV_RESULT; 
        3'b001: // add or sub
            #2 RESULT = ADD_RESULT;
        3'b010: // and
            #1 RESULT = AND_RESULT;
        3'b011: // or
            #1 RESULT = OR_RESULT;
        3'b100: // mult
            #2 RESULT = MULT_RESULT;
        3'b101: // sll
            #2 RESULT = SL_RESULT;
        //default: 3'b1xx is reserved        
        
        endcase
    end 
endmodule

Lab06/CPU Programming Tools-20240416/cpu.v
`include "alu.v"
`include "reg_file.v"

`define REG_ADDRESS_SIZE 3
`define REG_SIZE 8
`define OPCODE_SIZE 8
`define SH_AMT_SIZE 5
`define FUNC_SIZE 6
`define IMMIDIATE_SIZE 16
`define ADDRESS_SIZE 26

`define OPCODE_END 24
`define REGISTER_1_END 8
`define REGISTER_2_END 0
`define REGISTER_DEST_END 16

`define SH_AMT_END 6
`define FUNC_END 0
`define IMMIDIATE_END 0
`define ADDRESS_END 0
`define ALU_OP_SIZE 3


module mux_module(DATA1,DATA2,RESULT,SELECT);
    input [`REG_SIZE-1:0] DATA1;
    input [`REG_SIZE-1:0] DATA2;
    output reg [`REG_SIZE-1:0] RESULT; // if we want to use wire insted of reg , we woud have to use 'assign' to do that use internal_RESULT and assign to RESULT at the end
    input SELECT;

    always @(*) begin
        RESULT = SELECT ? DATA2 : DATA1;
    end

endmodule

module twos_complement(DATA,RESULT);
    input [`REG_SIZE-1:0] DATA;
    output reg [`REG_SIZE-1:0] RESULT;

    always @(DATA) begin
        #1 RESULT = ~DATA + 1'b1;
    end

endmodule


module programme_counter(RESULT,RESET,CLK);
    output reg [31:0] RESULT; 
    input RESET;
    input CLK;

    initial begin
        RESULT <= 32'd0;
    end

    always @(posedge CLK) begin
        #1
        if (RESET) begin
            RESULT <= 32'd0;
        end

        else begin
            RESULT <= RESULT + 32'd4;
        end
    end
    
endmodule



module instruction_decoder(INSTRUCTION,OPCODE,REGISTER_1,REGISTER_2,REGISTER_DEST,SH_AMT,FUNC,IMMIDIATE,ADDRESS);
    input [31:0] INSTRUCTION;
    output reg [`OPCODE_SIZE-1:0] OPCODE;
    output reg [`REG_ADDRESS_SIZE-1:0] REGISTER_1,REGISTER_2,REGISTER_DEST;
    output reg [`SH_AMT_SIZE-1:0] SH_AMT;
    output reg [`FUNC_SIZE-1:0] FUNC;
    output reg [`IMMIDIATE_SIZE-1:0] IMMIDIATE;
    output reg [`ADDRESS_SIZE-1:0] ADDRESS;

    always @(INSTRUCTION) begin
        #1
        OPCODE = INSTRUCTION[`OPCODE_END + `OPCODE_SIZE : `OPCODE_END];
        REGISTER_1 = INSTRUCTION[`REGISTER_1_END + `REG_SIZE : `REGISTER_1_END];
        REGISTER_2 = INSTRUCTION[`REGISTER_2_END + `REG_SIZE : `REGISTER_2_END];
        REGISTER_DEST = INSTRUCTION[`REGISTER_DEST_END + `REG_SIZE : `REGISTER_DEST_END];
        SH_AMT = INSTRUCTION[`SH_AMT_END + `SH_AMT_SIZE : `SH_AMT_END];
        FUNC = INSTRUCTION[`FUNC_END + `FUNC_SIZE : `FUNC_END];
        IMMIDIATE = INSTRUCTION[`IMMIDIATE_END + `IMMIDIATE_SIZE : `IMMIDIATE_END];
        ADDRESS = INSTRUCTION[`ADDRESS_END + `ADDRESS_SIZE : `ADDRESS_END];
    end

endmodule


// add, sub, and, or, mov, loadi
module control_unit(OPCODE,ALU_OP,ALU_SRC,REG_WRITE,TWOS_COMP);
    input [`OPCODE_SIZE-1:0] OPCODE;
    output reg REG_DEST,MEM_READ,MEM_TO_REG,MEM_WRITE,ALU_SRC,REG_WRITE,TWOS_COMP;
    output reg [`ALU_OP_SIZE-1:0] ALU_OP;

    // always block * to run the block whenever any input changes  
    always @(*)
    begin
        case (OPCODE) 
        8'b00000000: // loadi
        begin
            // REG_DEST = 1'b0;
            // JUMP = 1'b0;
            // BRANCH = 1'b0;
            // MEM_READ = 1'b0;
            // MEM_TO_REG = 1'b1;
            ALU_OP = 3'b000; //ALUOP COMMAND
            TWOS_COMP = 1'b0;
            // MEM_WRITE = 1'b0;
            ALU_SRC = 1'b1;
            REG_WRITE = 1'b0;
        end
        8'b00000001: // mov
        begin
            // REG_DEST = 1'b1;
            // JUMP = 1'b0;
            // BRANCH = 1'b0;
            // MEM_READ = 1'b0;
            // MEM_TO_REG = 1'b0;
            ALU_OP = 3'b000; //ALUOP COMMAND
            TWOS_COMP = 1'b0;
            // MEM_WRITE = 1'b0;
            ALU_SRC = 1'b0;
            REG_WRITE = 1'b1;     
        end   
        8'b00000010: // add
        begin
            // REG_DEST = 1'b1;
            // JUMP = 1'b0;
            // BRANCH = 1'b0;
            // MEM_READ = 1'b0;
            // MEM_TO_REG = 1'b0;
            ALU_OP = 3'b001; //ALUOP COMMAND
            TWOS_COMP = 1'b0;
            // MEM_WRITE = 1'b0;
            ALU_SRC = 1'b0;
            REG_WRITE = 1'b1;   
        end
        8'b00000011: // sub
        begin
            // REG_DEST = 1'b1;
            // JUMP = 1'b0;
            // BRANCH = 1'b0;
            // MEM_READ = 1'b0;
            // MEM_TO_REG = 1'b0;
            ALU_OP = 3'b001; //ALUOP COMMAND
            TWOS_COMP = 1'b1;
            // MEM_WRITE = 1'b0;
            ALU_SRC = 1'b0;
            REG_WRITE = 1'b1;   
        end
        8'b00000100: // and
        begin
            // REG_DEST = 1'b1;
            // JUMP = 1'b0;
            // BRANCH = 1'b0;
            // MEM_READ = 1'b0;
            // MEM_TO_REG = 1'b0;
            ALU_OP = 3'b010; //ALUOP COMMAND
            TWOS_COMP = 1'b0;
            // MEM_WRITE = 1'b0;
            ALU_SRC = 1'b0;
            REG_WRITE = 1'b1;  
        end  
        8'b00000101: // or
        begin
            // REG_DEST = 1'b0;
            // JUMP = 1'b0;
            // BRANCH = 1'b0;
            // MEM_READ = 1'b0;
            // MEM_TO_REG = 1'b1;
            ALU_OP = 3'b011; //ALUOP COMMAND
            TWOS_COMP = 1'b0;
            // MEM_WRITE = 1'b0;
            ALU_SRC = 1'b0;
            REG_WRITE = 1'b0;   
        end  
        //default: 3'b1xx is reserved        

	// char *op_loadi 	= "00000000";
	// char *op_mov 	= "00000001";
	// char *op_add 	= "00000010";
	// char *op_sub 	= "00000011";
	// char *op_and 	= "00000100";
	// char *op_or 	    = "00000101";
	// char *op_j		= "00000110";
	// char *op_beq	    = "00000111";
	// char *op_lwd 	= "00001000";
	// char *op_lwi 	= "00001001";
	// char *op_swd 	= "00001010";
	// char *op_swi 	= "00001011";

        endcase
    end 

endmodule


module cpu(PCOUT, INSTRUCTION, CLK, RESET);
    input wire [31:0] INSTRUCTION;
    input wire CLK;
    input wire RESET;
    output wire [31:0] PCOUT;

    //instruction_decoder
    wire [`REG_SIZE-1:0] IMMIDIATE;
    wire [`REG_ADDRESS_SIZE-1:0] READREG2;
    wire [`REG_ADDRESS_SIZE-1:0] READREG1;
    wire [`REG_ADDRESS_SIZE-1:0] WRITEREG;
    wire [`OPCODE_SIZE-1:0] OPCODE;

    //control_unit
    wire WRITEENABLE;
    wire REGMUXSELECT;
    wire ALUINMUX;
    wire [`ALU_OP_SIZE-1:0] ALUOP;

    //register_file
    wire [`REG_SIZE-1:0] REGOUT2;
    wire [`REG_SIZE-1:0] REGOUT1;

    //twos_compliment
    wire [`REG_SIZE-1:0] TWOS_COMP;

    //mux
    wire [`REG_SIZE-1:0] TWOS_COMP_SELECT;
    wire [`REG_SIZE-1:0] ALUMUXOUT;
    // wire [`REG_ADDRESS_SIZE-1:0] SELECTED_WRITEREG;

    //alu
    wire [`REG_SIZE-1:0] ALURESULT;

    programme_counter pc(PCOUT,RESET,CLK);


    control_unit CU(OPCODE,ALUOP,ALUINMUX,WRITEENABLE,REGMUXSELECT);


    // mux_module write_reg_selector(READREG2,IMMIDIATE,ALUMUXOUT,ALUINMUX);
    reg_file reg_file(ALURESULT,REGOUT1,REGOUT2,WRITEREG,READREG1,READREG2,WRITEENABLE,CLK,RESET);
    twos_complement twoscomp(REGOUT2,TWOS_COMP);
    mux_module register_out_mux(REGOUT2,TWOS_COMP,TWOS_COMP_SELECT,REGMUXSELECT);
    mux_module alu_in_mux(TWOS_COMP_SELECT,IMMIDIATE,ALUMUXOUT,ALUINMUX);
    alu alu(REGOUT1,TWOS_COMP_SELECT,ALURESULT,ALURESULT);



endmodule

Lab05Part5/CPU Programming Tools-20240416/instructiondecoder_tb.v

`include "cpu.v"

`define REG_ADDRESS_SIZE 3
`define REG_SIZE 8
`define OPCODE_SIZE 8
`define SH_AMT_SIZE 5
`define FUNC_SIZE 6
`define IMMIDIATE_SIZE 8
`define ADDRESS_SIZE 26

`define OPCODE_END 24
`define REGISTER_1_END 8
`define REGISTER_2_END 0
`define REGISTER_DEST_END 16

`define SH_AMT_END 6
`define FUNC_END 0
`define IMMIDIATE_END 0
`define ADDRESS_END 0
`define ALU_OP_SIZE 3

module instruction_decoder_tb;
reg [31:0] INSTRUCTION;
wire [`OPCODE_SIZE-1:0] OPCODE;
wire [`REG_ADDRESS_SIZE-1:0] REGISTER_1,REGISTER_2,REGISTER_DEST;
wire [`SH_AMT_SIZE-1:0] SH_AMT;
wire [`FUNC_SIZE-1:0] FUNC;
wire [`IMMIDIATE_SIZE-1:0] IMMIDIATE;
wire [`ADDRESS_SIZE-1:0] ADDRESS;

instruction_decoder decoder(INSTRUCTION,OPCODE,REGISTER_1,REGISTER_2,REGISTER_DEST,SH_AMT,FUNC,IMMIDIATE,ADDRESS);

   initial
    begin
        # 2 // Latency for instruction register
        // Manually written
        INSTRUCTION = 32'b00000000_00000100_00000000_00000101; // loadi 4 0x05
        #2
        INSTRUCTION = 32'b00000000_00000010_00000000_00001001; // loadi 2 0x09
        #2
        INSTRUCTION = 32'b00000010_00000110_00000100_00000010; // add 6 4 2
        #2
        INSTRUCTION = 32'b00000001_00000000_00000000_00000110; // mov 0 6
        #2
        INSTRUCTION = 32'b00000000_00000001_00000000_00000001; // loadi 1 0x01
        #2
        INSTRUCTION = 32'b00000010_00000010_00000010_00000001; // add 2 2 1
        
    end

    initial begin
        // generate files needed to plot the waveform using GTKWave
        $dumpfile("instruction_decoder_wavedata.vcd");
		$dumpvars(0, instruction_decoder_tb);
        // CLK = 1'b0;

        #20
        $finish;
    end
    
endmodule

Lab06/CPU Programming Tools-20240416/instruction_decoder_wavedata.vcd
$date
	Wed Apr 24 14:07:06 2024
$end
$version
	Icarus Verilog
$end
$timescale
	1s
$end
$scope module instruction_decoder_tb $end
$var wire 5 ! SH_AMT [4:0] $end
$var wire 3 " REGISTER_DEST [2:0] $end
$var wire 3 # REGISTER_2 [2:0] $end
$var wire 3 $ REGISTER_1 [2:0] $end
$var wire 8 % OPCODE [7:0] $end
$var wire 8 & IMMIDIATE [7:0] $end
$var wire 6 ' FUNC [5:0] $end
$var wire 26 ( ADDRESS [25:0] $end
$var reg 32 ) INSTRUCTION [31:0] $end
$scope module decoder $end
$var wire 32 * INSTRUCTION [31:0] $end
$var reg 26 + ADDRESS [25:0] $end
$var reg 6 , FUNC [5:0] $end
$var reg 8 - IMMIDIATE [7:0] $end
$var reg 8 . OPCODE [7:0] $end
$var reg 3 / REGISTER_1 [2:0] $end
$var reg 3 0 REGISTER_2 [2:0] $end
$var reg 3 1 REGISTER_DEST [2:0] $end
$var reg 5 2 SH_AMT [4:0] $end
$upscope $end
$upscope $end
$enddefinitions $end
$comment Show the parameter values. $end
$dumpall
$end
#0
$dumpvars
bx 2
bx 1
bx 0
bx /
bx .
bx -
bx ,
bx +
bx *
bx )
bx (
bx '
bx &
bx %
bx $
bx #
bx "
bx !
$end
#2
b1000000000000000101 )
b1000000000000000101 *
#3
b1000000000000000101 (
b1000000000000000101 +
b101 &
b101 -
b101 '
b101 ,
b0 !
b0 2
b100 "
b100 1
b101 #
b101 0
b0 $
b0 /
b0 %
b0 .
#4
b100000000000001001 )
b100000000000001001 *
#5
b100000000000001001 (
b100000000000001001 +
b1001 &
b1001 -
b1001 '
b1001 ,
b10 "
b10 1
b1 #
b1 0
#6
b10000001100000010000000010 )
b10000001100000010000000010 *
#7
b10000001100000010000000010 (
b10000001100000010000000010 +
b10 &
b10 -
b10 '
b10 ,
b10000 !
b10000 2
b110 "
b110 1
b10 #
b10 0
b100 $
b100 /
b10 %
b10 .
#8
b1000000000000000000000110 )
b1000000000000000000000110 *
#9
b1000000000000000000000110 (
b1000000000000000000000110 +
b110 &
b110 -
b110 '
b110 ,
b0 !
b0 2
b0 "
b0 1
b110 #
b110 0
b0 $
b0 /
b1 %
b1 .
#10
b10000000000000001 )
b10000000000000001 *
#11
b10000000000000001 (
b10000000000000001 +
b1 &
b1 -
b1 '
b1 ,
b1 "
b1 1
b1 #
b1 0
b0 %
b0 .
#12
b10000000100000001000000001 )
b10000000100000001000000001 *
#13
b10000000100000001000000001 (
b10000000100000001000000001 +
b1000 !
b1000 2
b10 "
b10 1
b10 $
b10 /
b10 %
b10 .
