Lab05/alu.v
module mov_module (data2,result);
    input [7:0] data2;
    output [7:0] result;

    assign result = data2;

endmodule

module add_module (data1,data2,result);
    input [7:0] data1;
    input [7:0] data2;
    output [7:0] result;

    assign result = data1 + data2;

endmodule

module sub_module (data1,data2,result);
    input [7:0] data1;
    input [7:0] data2;
    output [7:0] result;

    assign result = data1 - data2;

endmodule

module and_module (data1,data2,result);
    input [7:0] data1;
    input [7:0] data2;
    output [7:0] result;

    assign result = data1 & data2;

endmodule

module or_module (data1,data2,result);
    input [7:0] data1;
    input [7:0] data2;
    output [7:0] result;

    assign result = data1 | data2;

endmodule

module alu (data1,data2,result,select);
    input [7:0] data1;
    input [7:0] data2;
    output reg [7:0] result; // if we want to use wire insted of reg , we woud have to use 'assign' to do that use internal_result and assign to result at the end
    input [2:0] select;

    // making wires to have each module's answer.
    wire [7:0] mov_result;     
    wire [7:0] add_result;
    wire [7:0] sub_result;
    wire [7:0] and_result;
    wire [7:0] or_result;

    // making instences for each module with seperated output 
    mov_module u0(data2, mov_result);
    add_module u1(data1, data2, add_result);
    sub_module u2(data1, data2, sub_result);
    and_module u3(data1, data2, and_result);
    or_module u4(data1, data2, or_result);

    // always block * to run the block whenever any input changes  
    always @(*)
    begin
        case (select) //to select what to output as a mux
        3'b000: // forward
            #1 result = mov_result; 
        3'b001: begin // add - sub
            if (data2 < 0)  // or we can use (data2[7]) as the condition
                #2 result = sub_result;
            else
                #2 result = add_result;
            end

        3'b010: // and
            #1 result = and_result;
        3'b011: // or
            #1 result = or_result;
        //default: 3'b1xx is reserved        
        
        endcase
    end 
endmodule

Lab05/group19_lab5_part1/alu_tb.v
`timescale 1ns / 1ps
`include "alu.v"

module alu_tb;

// Inputs
reg [7:0] data1;
reg [7:0] data2;
reg [2:0] select;

// Output
wire [7:0] result;

// Instantiate the ALU module
alu alu_instance (
    .data1(data1), 
    .data2(data2), 
    .result(result), 
    .select(select)
);

initial begin
    $dumpfile("alu_tb.vcd");
    $dumpvars(0, alu_instance);
    // Initialize Inputs
    data1 = 0;
    data2 = 0;
    select = 3'b000;

    // Wait 10 ns for global reset to finish
    #10;
    
    // Test forward operation
    data1 = 8'hAA; // Example data
    data2 = 8'h55; // Example data
    select = 3'b000;
    #10; // Wait for the operation to complete

    // Test addition operation
    data2 = 8'h03; // Positive data2 for addition
    select = 3'b001;
    #10; // Wait for the operation to complete

    // Test subtraction operation
    data2 = -8'h03; // Negative data2 for subtraction
    select = 3'b001;
    #10; // Wait for the operation to complete

    // Test AND operation
    select = 3'b010;
    #10; // Wait for the operation to complete

    // Test OR operation
    select = 3'b011;
    #10; // Wait for the operation to complete

    // Finish the simulation
    $finish;
end

endmodule

Lab05/alu_tb.vcd
$date
	Tue Apr 09 21:18:59 2024
$end
$version
	Icarus Verilog
$end
$timescale
	1ps
$end
$scope module alu_tb $end
$scope module alu_instance $end
$var wire 8 ! data1 [7:0] $end
$var wire 8 " data2 [7:0] $end
$var wire 3 # select [2:0] $end
$var wire 8 $ sub_result [7:0] $end
$var wire 8 % or_result [7:0] $end
$var wire 8 & mov_result [7:0] $end
$var wire 8 ' and_result [7:0] $end
$var wire 8 ( add_result [7:0] $end
$var reg 8 ) result [7:0] $end
$scope module u0 $end
$var wire 8 * data2 [7:0] $end
$var wire 8 + result [7:0] $end
$upscope $end
$scope module u1 $end
$var wire 8 , data1 [7:0] $end
$var wire 8 - data2 [7:0] $end
$var wire 8 . result [7:0] $end
$upscope $end
$scope module u2 $end
$var wire 8 / data1 [7:0] $end
$var wire 8 0 data2 [7:0] $end
$var wire 8 1 result [7:0] $end
$upscope $end
$scope module u3 $end
$var wire 8 2 data1 [7:0] $end
$var wire 8 3 data2 [7:0] $end
$var wire 8 4 result [7:0] $end
$upscope $end
$scope module u4 $end
$var wire 8 5 data1 [7:0] $end
$var wire 8 6 data2 [7:0] $end
$var wire 8 7 result [7:0] $end
$upscope $end
$upscope $end
$upscope $end
$enddefinitions $end
$comment Show the parameter values. $end
$dumpall
$end
#0
$dumpvars
b0 7
b0 6
b0 5
b0 4
b0 3
b0 2
b0 1
b0 0
b0 /
b0 .
b0 -
b0 ,
b0 +
b0 *
bx )
b0 (
b0 '
b0 &
b0 %
b0 $
b0 #
b0 "
b0 !
$end
#1000
b0 )
#10000
b11111111 %
b11111111 7
b1010101 &
b1010101 +
b1010101 "
b1010101 *
b1010101 -
b1010101 0
b1010101 3
b1010101 6
b11111111 (
b11111111 .
b1010101 $
b1010101 1
b10101010 !
b10101010 ,
b10101010 /
b10101010 2
b10101010 5
#11000
b1010101 )
#20000
b10 '
b10 4
b10101011 %
b10101011 7
b1 #
b11 &
b11 +
b10101101 (
b10101101 .
b10100111 $
b10100111 1
b11 "
b11 *
b11 -
b11 0
b11 3
b11 6
#22000
b10101101 )
#30000
b10101000 '
b10101000 4
b11111111 %
b11111111 7
b11111101 &
b11111101 +
b10100111 (
b10100111 .
b10101101 $
b10101101 1
b11111101 "
b11111101 *
b11111101 -
b11111101 0
b11111101 3
b11111101 6
#32000
b10100111 )
#40000
b10 #
#41000
b10101000 )
#50000
b11 #
#51000
b11111111 )
