Lab05/group19_lab5_part2/reg_file.v
module reg_file(IN,OUT1,OUT2,INADDRESS,OUT1ADDRESS,OUT2ADDRESS, WRITE, CLK, RESET);
    input [7:0] IN;
    input [2:0] OUT1ADDRESS, OUT2ADDRESS, INADDRESS;
    output [7:0] OUT1, OUT2;
    input WRITE, CLK, RESET;

    // Internal register array
    reg [7:0] registers[7:0];

    // Output register (registers required since we cant assign if not registers)
    reg [7:0] out1_reg;
    reg [7:0] out2_reg;

    // Assign outputs to internal latches
    assign OUT1 = out1_reg;         
    assign OUT2 = out2_reg;
    
    always @(posedge CLK)
    begin
        if (RESET) // If reset is high
        begin
            // Reset all registers to 0 with time delay of #1
            registers[0] <= #1 8'b0;
            registers[1] <= #1 8'b0;
            registers[2] <= #1 8'b0;
            registers[3] <= #1 8'b0;
            registers[4] <= #1 8'b0;
            registers[5] <= #1 8'b0;
            registers[6] <= #1 8'b0;
            registers[7] <= #1 8'b0;
        end
        
        else if (WRITE) // If write is high
        begin
            registers[INADDRESS] <= #1 IN; // #1 propergation delay
        end
        
        else  // Else times output should be what ever address the pointers are pointing at
        begin   // Outputting values with #2 delay 
            out1_reg <= #2 registers[OUT1ADDRESS];      //here registers are reqired , since wirescant be used to store values
            out2_reg <= #2 registers[OUT2ADDRESS];
        end

    end

endmodule

Lab06/CPU Programming Tools-20240416/reg_file_tb.v
// Computer Architecture (CO224) - Lab 05
// Design: Register File of Simple Processor
// Author: Kisaru Liyanage
`include "reg_file.v"

module reg_file_tb;
    
    reg [7:0] WRITEDATA;
    reg [2:0] WRITEREG, READREG1, READREG2;
    reg CLK, RESET, WRITEENABLE; 
    wire [7:0] REGOUT1, REGOUT2;
    
    reg_file myregfile(WRITEDATA, REGOUT1, REGOUT2, WRITEREG, READREG1, READREG2, WRITEENABLE, CLK, RESET);
       
    initial
    begin
        CLK = 1'b1;
        
        // generate files needed to plot the waveform using GTKWave
        $dumpfile("reg_file_wavedata.vcd");
		$dumpvars(0, reg_file_tb);
        
        // assign values with time to input signals to see output 
        RESET = 1'b0;
        WRITEENABLE = 1'b0;
        
        #4
        RESET = 1'b1;
        READREG1 = 3'd0;
        READREG2 = 3'd4;
        
        #6
        RESET = 1'b0;
        
        #2
        WRITEREG = 3'd2;
        WRITEDATA = 8'd95;
        WRITEENABLE = 1'b1;
        
        #7
        WRITEENABLE = 1'b0;
        
        #1
        READREG1 = 3'd2;
        
        #7
        WRITEREG = 3'd1;
        WRITEDATA = 8'd28;
        WRITEENABLE = 1'b1;
        READREG1 = 3'd1;
        
        #8
        WRITEENABLE = 1'b0;
        
        #8
        WRITEREG = 3'd4;
        WRITEDATA = 8'd6;
        WRITEENABLE = 1'b1;
        
        #8
        WRITEDATA = 8'd15;
        WRITEENABLE = 1'b1;
        
        #10
        WRITEENABLE = 1'b0;
        
        #6
        WRITEREG = -3'd1;
        WRITEDATA = 8'd50;
        WRITEENABLE = 1'b1;
        
        #5
        WRITEENABLE = 1'b0;
        
        #10
        $finish;
    end
    
    // clock signal generation
    always
        #4 CLK = ~CLK;
        

endmodule

Lab05/reg_file_wavedata.vcd
$date
	Mon Apr 08 23:27:36 2024
$end
$version
	Icarus Verilog
$end
$timescale
	1s
$end
$scope module reg_file_tb $end
$var wire 8 ! REGOUT2 [7:0] $end
$var wire 8 " REGOUT1 [7:0] $end
$var reg 1 # CLK $end
$var reg 3 $ READREG1 [2:0] $end
$var reg 3 % READREG2 [2:0] $end
$var reg 1 & RESET $end
$var reg 8 ' WRITEDATA [7:0] $end
$var reg 1 ( WRITEENABLE $end
$var reg 3 ) WRITEREG [2:0] $end
$scope module myregfile $end
$var wire 1 # CLK $end
$var wire 8 * IN [7:0] $end
$var wire 3 + INADDRESS [2:0] $end
$var wire 8 , OUT1 [7:0] $end
$var wire 3 - OUT1ADDRESS [2:0] $end
$var wire 8 . OUT2 [7:0] $end
$var wire 3 / OUT2ADDRESS [2:0] $end
$var wire 1 & RESET $end
$var wire 1 ( WRITE $end
$var reg 8 0 out1_reg [7:0] $end
$var reg 8 1 out2_reg [7:0] $end
$upscope $end
$upscope $end
$enddefinitions $end
$comment Show the parameter values. $end
$dumpall
$end
#0
$dumpvars
bx 1
bx 0
bx /
bx .
bx -
bx ,
bx +
bx *
bx )
0(
bx '
0&
bx %
bx $
1#
bx "
bx !
$end
#4
0#
b100 %
b100 /
b0 $
b0 -
1&
#8
1#
#10
0&
#12
1(
b1011111 '
b1011111 *
b10 )
b10 +
0#
#16
1#
#19
0(
#20
b10 $
b10 -
0#
#24
1#
#26
b0 !
b0 .
b0 1
b1011111 "
b1011111 ,
b1011111 0
#27
b1 $
b1 -
1(
b11100 '
b11100 *
b1 )
b1 +
#28
0#
#32
1#
#35
0(
#36
0#
#40
1#
#42
b11100 "
b11100 ,
b11100 0
#43
1(
b110 '
b110 *
b100 )
b100 +
#44
0#
#48
1#
#51
b1111 '
b1111 *
#52
0#
#56
1#
#60
0#
#61
0(
#64
1#
#66
b1111 !
b1111 .
b1111 1
#67
1(
b110010 '
b110010 *
b111 )
b111 +
#68
0#
#72
1#
0(
