Lab05/alu.v
module alu (data1,data2,result,select);
    input [7:0] data1;
    input [7:0] data2;
    output reg [7:0] result; // if we want to use wire insted of reg , we woud have to use 'assign' to do that use internal_result and assign to result at the end
    input [2:0] select;

    //always block * to run the block whenever any input changes  
    always @(*)
    begin
        case (select) //to select what to output as a mux
        3'b000: // forward
            #1 result = data2; 
        3'b001: begin // add - sub
            if (data2 < 0)  // or we can use (data2[7]) as the condition
                #2 result = data1 - data2;
            else
                #2 result = data1 + data2;
            end

        3'b010: // and
            #1 result = data1 & data2;
        3'b011: // or
            #1 result = data1 | data2;
        // default: 3'b1xx is reserved        
        
        endcase
    end 

endmodule

Lab05/group19_lab5_part1/alu_tb.v
`timescale 1ns / 1ps
`include "alu.v"

module alu_tb;

// Inputs
reg [7:0] data1;
reg [7:0] data2;
reg [2:0] select;

// Output
wire [7:0] result;

// Instantiate the ALU module
alu alu_instance (
    .data1(data1), 
    .data2(data2), 
    .result(result), 
    .select(select)
);

initial begin
    $dumpfile("alu_tb.vcd");
    $dumpvars(0, alu_instance);
    // Initialize Inputs
    data1 = 0;
    data2 = 0;
    select = 3'b000;

    // Wait 10 ns for global reset to finish
    #10;
    
    // Test forward operation
    data1 = 8'hAA; // Example data
    data2 = 8'h55; // Example data
    select = 3'b000;
    #10; // Wait for the operation to complete

    // Test addition operation
    data2 = 8'h03; // Positive data2 for addition
    select = 3'b001;
    #10; // Wait for the operation to complete

    // Test subtraction operation
    data2 = -8'h03; // Negative data2 for subtraction
    select = 3'b001;
    #10; // Wait for the operation to complete

    // Test AND operation
    select = 3'b010;
    #10; // Wait for the operation to complete

    // Test OR operation
    select = 3'b011;
    #10; // Wait for the operation to complete

    // Finish the simulation
    $finish;
end

endmodule

Lab05/uut.vcd
$date
	Mon Apr 08 00:24:54 2024
$end
$version
	Icarus Verilog
$end
$timescale
	1ps
$end
$scope module alu_tb $end
$scope module uut $end
$var wire 8 ! data1 [7:0] $end
$var wire 8 " data2 [7:0] $end
$var wire 3 # select [2:0] $end
$var reg 8 $ result [7:0] $end
$upscope $end
$upscope $end
$enddefinitions $end
$comment Show the parameter values. $end
$dumpall
$end
#0
$dumpvars
bx $
b0 #
b0 "
b0 !
$end
#1
b0 $
#10
b1010101 "
b10101010 !
#11
b1010101 $
#20
b1 #
#22
b11111111 $
#30
b10 #
#31
b0 $
#40
b11 #
#41
b11111111 $
